Workbook
Name Slicer_Business_Unit: #N/A
Name Slicer_Country: #N/A
Name Slicer_Department: #N/A
Name Slicer_Employee_Status: #N/A

Sheet tbl-employees
A1: EEID | B1: Full Name | C1: Job Title | D1: Department | E1: Business Unit | F1: Gender | G1: Ethnicity | H1: Age | I1: Hire Date | J1: Annual Salary | K1: Bonus % | L1: Country | M1: City | N1: Exit Date | O1: Bonus Amount | P1: Total Compensation | Q1: Employee Status | R1: Tenure | S1: Age Band
A2: E02387 | B2: Emily Davis | C2: Sr. Manger | D2: IT | E2: Research & Development | F2: Female | G2: Black | H2: 55 | I2: 42468 | J2: 141604 | K2: 0.15 | L2: United States | M2: Seattle | N2: 44485 | O2: =J2*K2 -> 21240.6 | P2: =Table1[[#This Row],[Annual Salary]]+Table1[[#This Row],[Bonus Amount]] -> 162844.6 | Q2: =IF(Table1[[#This Row],[Exit Date]]="", "Active","Exited") -> Exited | R2: =IFERROR(DATEDIF(Table1[[#This Row],[Hire Date]],IF(Table1[[#This Row],[Exit Date]]="",TODAY(),Table1[[#This Row],[Exit Date]]),"Y"),"") -> 5 | S2: {=_xlfn.IFS(Table1[[#This Row],[Age]]<30,"Under 30",Table1[[#This Row],[Age]]<=40,"30-40",Table1[[#This Row],[Age]]<50,"41-50",TRUE,"50+")} -> 50+
A3: E04105 | B3: Theodore Dinh | C3: Technical Architect | D3: IT | E3: Manufacturing | F3: Male | G3: Asian | H3: 59 | I3: 35763 | J3: 99975 | K3: 0 | L3: China | M3: Chongqing | O3: =J3*K3 -> 0 | P3: =Table1[[#This Row],[Annual Salary]]+Table1[[#This Row],[Bonus Amount]] -> 99975 | Q3: =IF(Table1[[#This Row],[Exit Date]]="", "Active","Exited") -> Active | R3: =IFERROR(DATEDIF(Table1[[#This Row],[Hire Date]],IF(Table1[[#This Row],[Exit Date]]="",TODAY(),Table1[[#This Row],[Exit Date]]),"Y"),"") -> 28 | S3: {=_xlfn.IFS(Table1[[#This Row],[Age]]<30,"Under 30",Table1[[#This Row],[Age]]<=40,"30-40",Table1[[#This Row],[Age]]<50,"41-50",TRUE,"50+")} -> 50+
A4: E02572 | B4: Luna Sanders | C4: Director | D4: Finance | E4: Speciality Products | F4: Female | G4: Caucasian | H4: 50 | I4: 39016 | J4: 163099 | K4: 0.2 | L4: United States | M4: Chicago | O4: =J4*K4 -> 32619.8 | P4: =Table1[[#This Row],[Annual Salary]]+Table1[[#This Row],[Bonus Amount]] -> 195718.8 | Q4: =IF(Table1[[#This Row],[Exit Date]]="", "Active","Exited") -> Active | R4: =IFERROR(DATEDIF(Table1[[#This Row],[Hire Date]],IF(Table1[[#This Row],[Exit Date]]="",TODAY(),Table1[[#This Row],[Exit Date]]),"Y"),"") -> 19 | S4: {=_xlfn.IFS(Table1[[#This Row],[Age]]<30,"Under 30",Table1[[#This Row],[Age]]<=40,"30-40",Table1[[#This Row],[Age]]<50,"41-50",TRUE,"50+")} -> 50+
A5: E02832 | B5: Penelope Jordan | C5: Computer Systems Manager | D5: IT | E5: Manufacturing | F5: Female | G5: Caucasian | H5: 26 | I5: 43735 | J5: 84913 | K5: 0.07 | L5: United States | M5: Chicago | O5: =J5*K5 -> 5943.91 | P5: =Table1[[#This Row],[Annual Salary]]+Table1[[#This Row],[Bonus Amount]] -> 90856.91 | Q5: =IF(Table1[[#This Row],[Exit Date]]="", "Active","Exited") -> Active | R5: =IFERROR(DATEDIF(Table1[[#This Row],[Hire Date]],IF(Table1[[#This Row],[Exit Date]]="",TODAY(),Table1[[#This Row],[Exit Date]]),"Y"),"") -> 6 | S5: {=_xlfn.IFS(Table1[[#This Row],[Age]]<30,"Under 30",Table1[[#This Row],[Age]]<=40,"30-40",Table1[[#This Row],[Age]]<50,"41-50",TRUE,"50+")} -> Under 30
A6: E01639 | B6: Austin Vo | C6: Sr. Analyst | D6: Finance | E6: Manufacturing | F6: Male | G6: Asian | H6: 55 | I6: 35023 | J6: 95409 | K6: 0 | L6: United States | M6: Phoenix | O6: =J6*K6 -> 0 | P6: =Table1[[#This Row],[Annual Salary]]+Table1[[#This Row],[Bonus Amount]] -> 95409 | Q6: =IF(Table1[[#This Row],[Exit Date]]="", "Active","Exited") -> Active | R6: =IFERROR(DATEDIF(Table1[[#This Row],[Hire Date]],IF(Table1[[#This Row],[Exit Date]]="",TODAY(),Table1[[#This Row],[Exit Date]]),"Y"),"") -> 30 | S6: {=_xlfn.IFS(Table1[[#This Row],[Age]]<30,"Under 30",Table1[[#This Row],[Age]]<=40,"30-40",Table1[[#This Row],[Age]]<50,"41-50",TRUE,"50+")} -> 50+
A7: E00644 | B7: Joshua Gupta | C7: Account Representative | D7: Sales | E7: Corporate | F7: Male | G7: Asian | H7: 57 | I7: 42759 | J7: 50994 | K7: 0 | L7: China | M7: Chongqing | O7: =J7*K7 -> 0 | P7: =Table1[[#This Row],[Annual Salary]]+Table1[[#This Row],[Bonus Amount]] -> 50994 | Q7: =IF(Table1[[#This Row],[Exit Date]]="", "Active","Exited") -> Active | R7: =IFERROR(DATEDIF(Table1[[#This Row],[Hire Date]],IF(Table1[[#This Row],[Exit Date]]="",TODAY(),Table1[[#This Row],[Exit Date]]),"Y"),"") -> 9 | S7: {=_xlfn.IFS(Table1[[#This Row],[Age]]<30,"Under 30",Table1[[#This Row],[Age]]<=40,"30-40",Table1[[#This Row],[Age]]<50,"41-50",TRUE,"50+")} -> 50+
A8: E01550 | B8: Ruby Barnes | C8: Manager | D8: IT | E8: Corporate | F8: Female | G8: Caucasian | H8: 27 | I8: 44013 | J8: 119746 | K8: 0.1 | L8: United States | M8: Phoenix | O8: =J8*K8 -> 11974.6 | P8: =Table1[[#This Row],[Annual Salary]]+Table1[[#This Row],[Bonus Amount]] -> 131720.6 | Q8: =IF(Table1[[#This Row],[Exit Date]]="", "Active","Exited") -> Active | R8: =IFERROR(DATEDIF(Table1[[#This Row],[Hire Date]],IF(Table1[[#This Row],[Exit Date]]="",TODAY(),Table1[[#This Row],[Exit Date]]),"Y"),"") -> 5 | S8: {=_xlfn.IFS(Table1[[#This Row],[Age]]<30,"Under 30",Table1[[#This Row],[Age]]<=40,"30-40",Table1[[#This Row],[Age]]<50,"41-50",TRUE,"50+")} -> Under 30
A9: E04332 | B9: Luke Martin | C9: Analyst | D9: Finance | E9: Manufacturing | F9: Male | G9: Black | H9: 25 | I9: 43967 | J9: 41336 | K9: 0 | L9: United States | M9: Miami | N9: 44336 | O9: =J9*K9 -> 0 | P9: =Table1[[#This Row],[Annual Salary]]+Table1[[#This Row],[Bonus Amount]] -> 41336 | Q9: =IF(Table1[[#This Row],[Exit Date]]="", "Active","Exited") -> Exited | R9: =IFERROR(DATEDIF(Table1[[#This Row],[Hire Date]],IF(Table1[[#This Row],[Exit Date]]="",TODAY(),Table1[[#This Row],[Exit Date]]),"Y"),"") -> 1 | S9: {=_xlfn.IFS(Table1[[#This Row],[Age]]<30,"Under 30",Table1[[#This Row],[Age]]<=40,"30-40",Table1[[#This Row],[Age]]<50,"41-50",TRUE,"50+")} -> Under 30
A10: E04533 | B10: Easton Bailey | C10: Manager | D10: Accounting | E10: Manufacturing | F10: Male | G10: Caucasian | H10: 29 | I10: 43490 | J10: 113527 | K10: 0.06 | L10: United States | M10: Austin | O10: =J10*K10 -> 6811.62 | P10: =Table1[[#This Row],[Annual Salary]]+Table1[[#This Row],[Bonus Amount]] -> 120338.62 | Q10: =IF(Table1[[#This Row],[Exit Date]]="", "Active","Exited") -> Active | R10: =IFERROR(DATEDIF(Table1[[#This Row],[Hire Date]],IF(Table1[[#This Row],[Exit Date]]="",TODAY(),Table1[[#This Row],[Exit Date]]),"Y"),"") -> 7 | S10: {=_xlfn.IFS(Table1[[#This Row],[Age]]<30,"Under 30",Table1[[#This Row],[Age]]<=40,"30-40",Table1[[#This Row],[Age]]<50,"41-50",TRUE,"50+")} -> Under 30
A11: E03838 | B11: Madeline Walker | C11: Sr. Analyst | D11: Finance | E11: Speciality Products | F11: Female | G11: Caucasian | H11: 34 | I11: 43264 | J11: 77203 | K11: 0 | L11: United States | M11: Chicago | O11: =J11*K11 -> 0 | P11: =Table1[[#This Row],[Annual Salary]]+Table1[[#This Row],[Bonus Amount]] -> 77203 | Q11: =IF(Table1[[#This Row],[Exit Date]]="", "Active","Exited") -> Active | R11: =IFERROR(DATEDIF(Table1[[#This Row],[Hire Date]],IF(Table1[[#This Row],[Exit Date]]="",TODAY(),Table1[[#This Row],[Exit Date]]),"Y"),"") -> 7 | S11: {=_xlfn.IFS(Table1[[#This Row],[Age]]<30,"Under 30",Table1[[#This Row],[Age]]<=40,"30-40",Table1[[#This Row],[Age]]<50,"41-50",TRUE,"50+")} -> 30-40
A12: E00591 | B12: Savannah Ali | C12: Sr. Manger | D12: Human Resources | E12: Manufacturing | F12: Female | G12: Asian | H12: 36 | I12: 39855 | J12: 157333 | K12: 0.15 | L12: United States | M12: Miami | O12: =J12*K12 -> 23599.95 | P12: =Table1[[#This Row],[Annual Salary]]+Table1[[#This Row],[Bonus Amount]] -> 180932.95 | Q12: =IF(Table1[[#This Row],[Exit Date]]="", "Active","Exited") -> Active | R12: =IFERROR(DATEDIF(Table1[[#This Row],[Hire Date]],IF(Table1[[#This Row],[Exit Date]]="",TODAY(),Table1[[#This Row],[Exit Date]]),"Y"),"") -> 17 | S12: {=_xlfn.IFS(Table1[[#This Row],[Age]]<30,"Under 30",Table1[[#This Row],[Age]]<=40,"30-40",Table1[[#This Row],[Age]]<50,"41-50",TRUE,"50+")} -> 30-40
A13: E03344 | B13: Camila Rogers | C13: Controls Engineer | D13: Engineering | E13: Speciality Products | F13: Female | G13: Caucasian | H13: 27 | I13: 44490 | J13: 109851 | K13: 0 | L13: United States | M13: Seattle | O13: =J13*K13 -> 0 | P13: =Table1[[#This Row],[Annual Salary]]+Table1[[#This Row],[Bonus Amount]] -> 109851 | Q13: =IF(Table1[[#This Row],[Exit Date]]="", "Active","Exited") -> Active | R13: =IFERROR(DATEDIF(Table1[[#This Row],[Hire Date]],IF(Table1[[#This Row],[Exit Date]]="",TODAY(),Table1[[#This Row],[Exit Date]]),"Y"),"") -> 4 | S13: {=_xlfn.IFS(Table1[[#This Row],[Age]]<30,"Under 30",Table1[[#This Row],[Age]]<=40,"30-40",Table1[[#This Row],[Age]]<50,"41-50",TRUE,"50+")} -> Under 30
A14: E00530 | B14: Eli Jones | C14: Manager | D14: Human Resources | E14: Manufacturing | F14: Male | G14: Caucasian | H14: 59 | I14: 36233 | J14: 105086 | K14: 0.09 | L14: United States | M14: Austin | O14: =J14*K14 -> 9457.74 | P14: =Table1[[#This Row],[Annual Salary]]+Table1[[#This Row],[Bonus Amount]] -> 114543.74 | Q14: =IF(Table1[[#This Row],[Exit Date]]="", "Active","Exited") -> Active | R14: =IFERROR(DATEDIF(Table1[[#This Row],[Hire Date]],IF(Table1[[#This Row],[Exit Date]]="",TODAY(),Table1[[#This Row],[Exit Date]]),"Y"),"") -> 27 | S14: {=_xlfn.IFS(Table1[[#This Row],[Age]]<30,"Under 30",Table1[[#This Row],[Age]]<=40,"30-40",Table1[[#This Row],[Age]]<50,"41-50",TRUE,"50+")} -> 50+
A15: E04239 | B15: Everleigh Ng | C15: Sr. Manger | D15: Finance | E15: Research & Development | F15: Female | G15: Asian | H15: 51 | I15: 44357 | J15: 146742 | K15: 0.1 | L15: China | M15: Shanghai | O15: =J15*K15 -> 14674.2 | P15: =Table1[[#This Row],[Annual Salary]]+Table1[[#This Row],[Bonus Amount]] -> 161416.2 | Q15: =IF(Table1[[#This Row],[Exit Date]]="", "Active","Exited") -> Active | R15: =IFERROR(DATEDIF(Table1[[#This Row],[Hire Date]],IF(Table1[[#This Row],[Exit Date]]="",TODAY(),Table1[[#This Row],[Exit Date]]),"Y"),"") -> 4 | S15: {=_xlfn.IFS(Table1[[#This Row],[Age]]<30,"Under 30",Table1[[#This Row],[Age]]<=40,"30-40",Table1[[#This Row],[Age]]<50,"41-50",TRUE,"50+")} -> 50+
A16: E03496 | B16: Robert Yang | C16: Sr. Analyst | D16: Accounting | E16: Speciality Products | F16: Male | G16: Asian | H16: 31 | I16: 43043 | J16: 97078 | K16: 0 | L16: United States | M16: Austin | N16: 43899 | O16: =J16*K16 -> 0 | P16: =Table1[[#This Row],[Annual Salary]]+Table1[[#This Row],[Bonus Amount]] -> 97078 | Q16: =IF(Table1[[#This Row],[Exit Date]]="", "Active","Exited") -> Exited | R16: =IFERROR(DATEDIF(Table1[[#This Row],[Hire Date]],IF(Table1[[#This Row],[Exit Date]]="",TODAY(),Table1[[#This Row],[Exit Date]]),"Y"),"") -> 2 | S16: {=_xlfn.IFS(Table1[[#This Row],[Age]]<30,"Under 30",Table1[[#This Row],[Age]]<=40,"30-40",Table1[[#This Row],[Age]]<50,"41-50",TRUE,"50+")} -> 30-40
A17: E00549 | B17: Isabella Xi | C17: Vice President | D17: Marketing | E17: Research & Development | F17: Female | G17: Asian | H17: 41 | I17: 41346 | J17: 249270 | K17: 0.3 | L17: United States | M17: Seattle | O17: =J17*K17 -> 74781 | P17: =Table1[[#This Row],[Annual Salary]]+Table1[[#This Row],[Bonus Amount]] -> 324051 | Q17: =IF(Table1[[#This Row],[Exit Date]]="", "Active","Exited") -> Active | R17: =IFERROR(DATEDIF(Table1[[#This Row],[Hire Date]],IF(Table1[[#This Row],[Exit Date]]="",TODAY(),Table1[[#This Row],[Exit Date]]),"Y"),"") -> 13 | S17: {=_xlfn.IFS(Table1[[#This Row],[Age]]<30,"Under 30",Table1[[#This Row],[Age]]<=40,"30-40",Table1[[#This Row],[Age]]<50,"41-50",TRUE,"50+")} -> 41-50
A18: E00163 | B18: Bella Powell | C18: Director | D18: Finance | E18: Research & Development | F18: Female | G18: Black | H18: 65 | I18: 37319 | J18: 175837 | K18: 0.2 | L18: United States | M18: Phoenix | O18: =J18*K18 -> 35167.4 | P18: =Table1[[#This Row],[Annual Salary]]+Table1[[#This Row],[Bonus Amount]] -> 211004.4 | Q18: =IF(Table1[[#This Row],[Exit Date]]="", "Active","Exited") -> Active | R18: =IFERROR(DATEDIF(Table1[[#This Row],[Hire Date]],IF(Table1[[#This Row],[Exit Date]]="",TODAY(),Table1[[#This Row],[Exit Date]]),"Y"),"") -> 24 | S18: {=_xlfn.IFS(Table1[[#This Row],[Age]]<30,"Under 30",Table1[[#This Row],[Age]]<=40,"30-40",Table1[[#This Row],[Age]]<50,"41-50",TRUE,"50+")} -> 50+
A19: E00884 | B19: Camila Silva | C19: Sr. Manger | D19: Marketing | E19: Speciality Products | F19: Female | G19: Latino | H19: 64 | I19: 37956 | J19: 154828 | K19: 0.13 | L19: United States | M19: Seattle | O19: =J19*K19 -> 20127.64 | P19: =Table1[[#This Row],[Annual Salary]]+Table1[[#This Row],[Bonus Amount]] -> 174955.64 | Q19: =IF(Table1[[#This Row],[Exit Date]]="", "Active","Exited") -> Active | R19: =IFERROR(DATEDIF(Table1[[#This Row],[Hire Date]],IF(Table1[[#This Row],[Exit Date]]="",TODAY(),Table1[[#This Row],[Exit Date]]),"Y"),"") -> 22 | S19: {=_xlfn.IFS(Table1[[#This Row],[Age]]<30,"Under 30",Table1[[#This Row],[Age]]<=40,"30-40",Table1[[#This Row],[Age]]<50,"41-50",TRUE,"50+")} -> 50+
A20: E04116 | B20: David Barnes | C20: Director | D20: IT | E20: Corporate | F20: Male | G20: Caucasian | H20: 64 | I20: 41581 | J20: 186503 | K20: 0.24 | L20: United States | M20: Columbus | O20: =J20*K20 -> 44760.72 | P20: =Table1[[#This Row],[Annual Salary]]+Table1[[#This Row],[Bonus Amount]] -> 231263.72 | Q20: =IF(Table1[[#This Row],[Exit Date]]="", "Active","Exited") -> Active | R20: =IFERROR(DATEDIF(Table1[[#This Row],[Hire Date]],IF(Table1[[#This Row],[Exit Date]]="",TODAY(),Table1[[#This Row],[Exit Date]]),"Y"),"") -> 12 | S20: {=_xlfn.IFS(Table1[[#This Row],[Age]]<30,"Under 30",Table1[[#This Row],[Age]]<=40,"30-40",Table1[[#This Row],[Age]]<50,"41-50",TRUE,"50+")} -> 50+
A21: E04625 | B21: Adam Dang | C21: Director | D21: Sales | E21: Research & Development | F21: Male | G21: Asian | H21: 45 | I21: 37446 | J21: 166331 | K21: 0.18 | L21: China | M21: Chongqing | O21: =J21*K21 -> 29939.58 | P21: =Table1[[#This Row],[Annual Salary]]+Table1[[#This Row],[Bonus Amount]] -> 196270.58 | Q21: =IF(Table1[[#This Row],[Exit Date]]="", "Active","Exited") -> Active | R21: =IFERROR(DATEDIF(Table1[[#This Row],[Hire Date]],IF(Table1[[#This Row],[Exit Date]]="",TODAY(),Table1[[#This Row],[Exit Date]]),"Y"),"") -> 23 | S21: {=_xlfn.IFS(Table1[[#This Row],[Age]]<30,"Under 30",Table1[[#This Row],[Age]]<=40,"30-40",Table1[[#This Row],[Age]]<50,"41-50",TRUE,"50+")} -> 41-50
A22: E03680 | B22: Elias Alvarado | C22: Sr. Manger | D22: IT | E22: Manufacturing | F22: Male | G22: Latino | H22: 56 | I22: 40917 | J22: 146140 | K22: 0.1 | L22: Brazil | M22: Manaus | O22: =J22*K22 -> 14614 | P22: =Table1[[#This Row],[Annual Salary]]+Table1[[#This Row],[Bonus Amount]] -> 160754 | Q22: =IF(Table1[[#This Row],[Exit Date]]="", "Active","Exited") -> Active | R22: =IFERROR(DATEDIF(Table1[[#This Row],[Hire Date]],IF(Table1[[#This Row],[Exit Date]]="",TODAY(),Table1[[#This Row],[Exit Date]]),"Y"),"") -> 14 | S22: {=_xlfn.IFS(Table1[[#This Row],[Age]]<30,"Under 30",Table1[[#This Row],[Age]]<=40,"30-40",Table1[[#This Row],[Age]]<50,"41-50",TRUE,"50+")} -> 50+
A23: E04732 | B23: Eva Rivera | C23: Director | D23: Sales | E23: Manufacturing | F23: Female | G23: Latino | H23: 36 | I23: 44288 | J23: 151703 | K23: 0.21 | L23: United States | M23: Miami | O23: =J23*K23 -> 31857.63 | P23: =Table1[[#This Row],[Annual Salary]]+Table1[[#This Row],[Bonus Amount]] -> 183560.63 | Q23: =IF(Table1[[#This Row],[Exit Date]]="", "Active","Exited") -> Active | R23: =IFERROR(DATEDIF(Table1[[#This Row],[Hire Date]],IF(Table1[[#This Row],[Exit Date]]="",TODAY(),Table1[[#This Row],[Exit Date]]),"Y"),"") -> 4 | S23: {=_xlfn.IFS(Table1[[#This Row],[Age]]<30,"Under 30",Table1[[#This Row],[Age]]<=40,"30-40",Table1[[#This Row],[Age]]<50,"41-50",TRUE,"50+")} -> 30-40
A24: E03484 | B24: Logan Rivera | C24: Director | D24: IT | E24: Research & Development | F24: Male | G24: Latino | H24: 59 | I24: 37400 | J24: 172787 | K24: 0.28 | L24: Brazil | M24: Rio de Janerio | O24: =J24*K24 -> 48380.36 | P24: =Table1[[#This Row],[Annual Salary]]+Table1[[#This Row],[Bonus Amount]] -> 221167.36 | Q24: =IF(Table1[[#This Row],[Exit Date]]="", "Active","Exited") -> Active | R24: =IFERROR(DATEDIF(Table1[[#This Row],[Hire Date]],IF(Table1[[#This Row],[Exit Date]]="",TODAY(),Table1[[#This Row],[Exit Date]]),"Y"),"") -> 23 | S24: {=_xlfn.IFS(Table1[[#This Row],[Age]]<30,"Under 30",Table1[[#This Row],[Age]]<=40,"30-40",Table1[[#This Row],[Age]]<50,"41-50",TRUE,"50+")} -> 50+
A25: E00671 | B25: Leonardo Dixon | C25: Analyst | D25: Sales | E25: Speciality Products | F25: Male | G25: Caucasian | H25: 37 | I25: 43713 | J25: 49998 | K25: 0 | L25: United States | M25: Seattle | O25: =J25*K25 -> 0 | P25: =Table1[[#This Row],[Annual Salary]]+Table1[[#This Row],[Bonus Amount]] -> 49998 | Q25: =IF(Table1[[#This Row],[Exit Date]]="", "Active","Exited") -> Active | R25: =IFERROR(DATEDIF(Table1[[#This Row],[Hire Date]],IF(Table1[[#This Row],[Exit Date]]="",TODAY(),Table1[[#This Row],[Exit Date]]),"Y"),"") -> 6 | S25: {=_xlfn.IFS(Table1[[#This Row],[Age]]<30,"Under 30",Table1[[#This Row],[Age]]<=40,"30-40",Table1[[#This Row],[Age]]<50,"41-50",TRUE,"50+")} -> 30-40
A26: E02071 | B26: Mateo Her | C26: Vice President | D26: Sales | E26: Speciality Products | F26: Male | G26: Asian | H26: 44 | I26: 41700 | J26: 207172 | K26: 0.31 | L26: China | M26: Chongqing | O26: =J26*K26 -> 64223.32 | P26: =Table1[[#This Row],[Annual Salary]]+Table1[[#This Row],[Bonus Amount]] -> 271395.32 | Q26: =IF(Table1[[#This Row],[Exit Date]]="", "Active","Exited") -> Active | R26: =IFERROR(DATEDIF(Table1[[#This Row],[Hire Date]],IF(Table1[[#This Row],[Exit Date]]="",TODAY(),Table1[[#This Row],[Exit Date]]),"Y"),"") -> 12 | S26: {=_xlfn.IFS(Table1[[#This Row],[Age]]<30,"Under 30",Table1[[#This Row],[Age]]<=40,"30-40",Table1[[#This Row],[Age]]<50,"41-50",TRUE,"50+")} -> 41-50
A27: E02206 | B27: Jose Henderson | C27: Director | D27: Human Resources | E27: Speciality Products | F27: Male | G27: Black | H27: 41 | I27: 42111 | J27: 152239 | K27: 0.23 | L27: United States | M27: Columbus | O27: =J27*K27 -> 35014.97 | P27: =Table1[[#This Row],[Annual Salary]]+Table1[[#This Row],[Bonus Amount]] -> 187253.97 | Q27: =IF(Table1[[#This Row],[Exit Date]]="", "Active","Exited") -> Active | R27: =IFERROR(DATEDIF(Table1[[#This Row],[Hire Date]],IF(Table1[[#This Row],[Exit Date]]="",TODAY(),Table1[[#This Row],[Exit Date]]),"Y"),"") -> 10 | S27: {=_xlfn.IFS(Table1[[#This Row],[Age]]<30,"Under 30",Table1[[#This Row],[Age]]<=40,"30-40",Table1[[#This Row],[Age]]<50,"41-50",TRUE,"50+")} -> 41-50
A28: E04545 | B28: Abigail Mejia | C28: Quality Engineer | D28: Engineering | E28: Corporate | F28: Female | G28: Latino | H28: 56 | I28: 38388 | J28: 98581 | K28: 0 | L28: Brazil | M28: Rio de Janerio | O28: =J28*K28 -> 0 | P28: =Table1[[#This Row],[Annual Salary]]+Table1[[#This Row],[Bonus Amount]] -> 98581 | Q28: =IF(Table1[[#This Row],[Exit Date]]="", "Active","Exited") -> Active | R28: =IFERROR(DATEDIF(Table1[[#This Row],[Hire Date]],IF(Table1[[#This Row],[Exit Date]]="",TODAY(),Table1[[#This Row],[Exit Date]]),"Y"),"") -> 21 | S28: {=_xlfn.IFS(Table1[[#This Row],[Age]]<30,"Under 30",Table1[[#This Row],[Age]]<=40,"30-40",Table1[[#This Row],[Age]]<50,"41-50",TRUE,"50+")} -> 50+
... A41: E01417 | B41: Leah Pena | C41: Enterprise Architect | D41: IT | E41: Corporate | F41: Female | G41: Latino | H41: 57 | I41: 34337 | J41: 82872 | K41: 0 | L41: Brazil | M41: Manaus | O41: =J41*K41 -> 0 | P41: =Table1[[#This Row],[Annual Salary]]+Table1[[#This Row],[Bonus Amount]] -> 82872 | Q41: =IF(Table1[[#This Row],[Exit Date]]="", "Active","Exited") -> Active | R41: =IFERROR(DATEDIF(Table1[[#This Row],[Hire Date]],IF(Table1[[#This Row],[Exit Date]]="",TODAY(),Table1[[#This Row],[Exit Date]]),"Y"),"") -> 32 | S41: {=_xlfn.IFS(Table1[[#This Row],[Age]]<30,"Under 30",Table1[[#This Row],[Age]]<=40,"30-40",Table1[[#This Row],[Age]]<50,"41-50",TRUE,"50+")} -> 50+
A42: E01754 | B42: Owen Lam | C42: Sr. Business Partner | D42: Human Resources | E42: Speciality Products | F42: Male | G42: Asian | H42: 30 | I42: 42884 | J42: 86317 | K42: 0 | L42: China | M42: Chengdu | N42: 42932 | O42: =J42*K42 -> 0 | P42: =Table1[[#This Row],[Annual Salary]]+Table1[[#This Row],[Bonus Amount]] -> 86317 | Q42: =IF(Table1[[#This Row],[Exit Date]]="", "Active","Exited") -> Exited | R42: =IFERROR(DATEDIF(Table1[[#This Row],[Hire Date]],IF(Table1[[#This Row],[Exit Date]]="",TODAY(),Table1[[#This Row],[Exit Date]]),"Y"),"") -> 0 | S42: {=_xlfn.IFS(Table1[[#This Row],[Age]]<30,"Under 30",Table1[[#This Row],[Age]]<=40,"30-40",Table1[[#This Row],[Age]]<50,"41-50",TRUE,"50+")} -> 30-40
A43: E03749 | B43: Kennedy Foster | C43: Manager | D43: Marketing | E43: Speciality Products | F43: Female | G43: Caucasian | H43: 53 | I43: 41601 | J43: 113135 | K43: 0.05 | L43: United States | M43: Austin | O43: =J43*K43 -> 5656.75 | P43: =Table1[[#This Row],[Annual Salary]]+Table1[[#This Row],[Bonus Amount]] -> 118791.75 | Q43: =IF(Table1[[#This Row],[Exit Date]]="", "Active","Exited") -> Active | R43: =IFERROR(DATEDIF(Table1[[#This Row],[Hire Date]],IF(Table1[[#This Row],[Exit Date]]="",TODAY(),Table1[[#This Row],[Exit Date]]),"Y"),"") -> 12 | S43: {=_xlfn.IFS(Table1[[#This Row],[Age]]<30,"Under 30",Table1[[#This Row],[Age]]<=40,"30-40",Table1[[#This Row],[Age]]<50,"41-50",TRUE,"50+")} -> 50+
A44: E03574 | B44: John Moore | C44: Vice President | D44: IT | E44: Speciality Products | F44: Male | G44: Caucasian | H44: 52 | I44: 38664 | J44: 199808 | K44: 0.32 | L44: United States | M44: Seattle | O44: =J44*K44 -> 63938.56 | P44: =Table1[[#This Row],[Annual Salary]]+Table1[[#This Row],[Bonus Amount]] -> 263746.56 | Q44: =IF(Table1[[#This Row],[Exit Date]]="", "Active","Exited") -> Active | R44: =IFERROR(DATEDIF(Table1[[#This Row],[Hire Date]],IF(Table1[[#This Row],[Exit Date]]="",TODAY(),Table1[[#This Row],[Exit Date]]),"Y"),"") -> 20 | S44: {=_xlfn.IFS(Table1[[#This Row],[Age]]<30,"Under 30",Table1[[#This Row],[Age]]<=40,"30-40",Table1[[#This Row],[Age]]<50,"41-50",TRUE,"50+")} -> 50+
A45: E04600 | B45: William Vu | C45: Account Representative | D45: Sales | E45: Speciality Products | F45: Male | G45: Asian | H45: 37 | I45: 41592 | J45: 56037 | K45: 0 | L45: China | M45: Shanghai | O45: =J45*K45 -> 0 | P45: =Table1[[#This Row],[Annual Salary]]+Table1[[#This Row],[Bonus Amount]] -> 56037 | Q45: =IF(Table1[[#This Row],[Exit Date]]="", "Active","Exited") -> Active | R45: =IFERROR(DATEDIF(Table1[[#This Row],[Hire Date]],IF(Table1[[#This Row],[Exit Date]]="",TODAY(),Table1[[#This Row],[Exit Date]]),"Y"),"") -> 12 | S45: {=_xlfn.IFS(Table1[[#This Row],[Age]]<30,"Under 30",Table1[[#This Row],[Age]]<=40,"30-40",Table1[[#This Row],[Age]]<50,"41-50",TRUE,"50+")} -> 30-40
A46: E00586 | B46: Sadie Washington | C46: Sr. Manger | D46: Marketing | E46: Research & Development | F46: Female | G46: Caucasian | H46: 29 | I46: 43609 | J46: 122350 | K46: 0.12 | L46: United States | M46: Phoenix | O46: =J46*K46 -> 14682 | P46: =Table1[[#This Row],[Annual Salary]]+Table1[[#This Row],[Bonus Amount]] -> 137032 | Q46: =IF(Table1[[#This Row],[Exit Date]]="", "Active","Exited") -> Active | R46: =IFERROR(DATEDIF(Table1[[#This Row],[Hire Date]],IF(Table1[[#This Row],[Exit Date]]="",TODAY(),Table1[[#This Row],[Exit Date]]),"Y"),"") -> 6 | S46: {=_xlfn.IFS(Table1[[#This Row],[Age]]<30,"Under 30",Table1[[#This Row],[Age]]<=40,"30-40",Table1[[#This Row],[Age]]<50,"41-50",TRUE,"50+")} -> Under 30
A47: E03538 | B47: Gabriel Holmes | C47: Enterprise Architect | D47: IT | E47: Research & Development | F47: Male | G47: Caucasian | H47: 40 | I47: 40486 | J47: 92952 | K47: 0 | L47: United States | M47: Seattle | O47: =J47*K47 -> 0 | P47: =Table1[[#This Row],[Annual Salary]]+Table1[[#This Row],[Bonus Amount]] -> 92952 | Q47: =IF(Table1[[#This Row],[Exit Date]]="", "Active","Exited") -> Active | R47: =IFERROR(DATEDIF(Table1[[#This Row],[Hire Date]],IF(Table1[[#This Row],[Exit Date]]="",TODAY(),Table1[[#This Row],[Exit Date]]),"Y"),"") -> 15 | S47: {=_xlfn.IFS(Table1[[#This Row],[Age]]<30,"Under 30",Table1[[#This Row],[Age]]<=40,"30-40",Table1[[#This Row],[Age]]<50,"41-50",TRUE,"50+")} -> 30-40
A48: E02185 | B48: Wyatt Rojas | C48: Computer Systems Manager | D48: IT | E48: Corporate | F48: Male | G48: Latino | H48: 32 | I48: 41353 | J48: 79921 | K48: 0.05 | L48: United States | M48: Austin | O48: =J48*K48 -> 3996.05 | P48: =Table1[[#This Row],[Annual Salary]]+Table1[[#This Row],[Bonus Amount]] -> 83917.05 | Q48: =IF(Table1[[#This Row],[Exit Date]]="", "Active","Exited") -> Active | R48: =IFERROR(DATEDIF(Table1[[#This Row],[Hire Date]],IF(Table1[[#This Row],[Exit Date]]="",TODAY(),Table1[[#This Row],[Exit Date]]),"Y"),"") -> 13 | S48: {=_xlfn.IFS(Table1[[#This Row],[Age]]<30,"Under 30",Table1[[#This Row],[Age]]<=40,"30-40",Table1[[#This Row],[Age]]<50,"41-50",TRUE,"50+")} -> 30-40
A49: E03830 | B49: Eva Coleman | C49: Director | D49: IT | E49: Research & Development | F49: Female | G49: Black | H49: 37 | I49: 40076 | J49: 167199 | K49: 0.2 | L49: United States | M49: Seattle | O49: =J49*K49 -> 33439.8 | P49: =Table1[[#This Row],[Annual Salary]]+Table1[[#This Row],[Bonus Amount]] -> 200638.8 | Q49: =IF(Table1[[#This Row],[Exit Date]]="", "Active","Exited") -> Active | R49: =IFERROR(DATEDIF(Table1[[#This Row],[Hire Date]],IF(Table1[[#This Row],[Exit Date]]="",TODAY(),Table1[[#This Row],[Exit Date]]),"Y"),"") -> 16 | S49: {=_xlfn.IFS(Table1[[#This Row],[Age]]<30,"Under 30",Table1[[#This Row],[Age]]<=40,"30-40",Table1[[#This Row],[Age]]<50,"41-50",TRUE,"50+")} -> 30-40
A50: E03720 | B50: Dominic Clark | C50: Quality Engineer | D50: Engineering | E50: Research & Development | F50: Male | G50: Caucasian | H50: 52 | I50: 41199 | J50: 71476 | K50: 0 | L50: United States | M50: Phoenix | O50: =J50*K50 -> 0 | P50: =Table1[[#This Row],[Annual Salary]]+Table1[[#This Row],[Bonus Amount]] -> 71476 | Q50: =IF(Table1[[#This Row],[Exit Date]]="", "Active","Exited") -> Active | R50: =IFERROR(DATEDIF(Table1[[#This Row],[Hire Date]],IF(Table1[[#This Row],[Exit Date]]="",TODAY(),Table1[[#This Row],[Exit Date]]),"Y"),"") -> 13 | S50: {=_xlfn.IFS(Table1[[#This Row],[Age]]<30,"Under 30",Table1[[#This Row],[Age]]<=40,"30-40",Table1[[#This Row],[Age]]<50,"41-50",TRUE,"50+")} -> 50+
A51: E03025 | B51: Lucy Alexander | C51: Director | D51: Engineering | E51: Manufacturing | F51: Female | G51: Caucasian | H51: 45 | I51: 41941 | J51: 189420 | K51: 0.2 | L51: United States | M51: Seattle | O51: =J51*K51 -> 37884 | P51: =Table1[[#This Row],[Annual Salary]]+Table1[[#This Row],[Bonus Amount]] -> 227304 | Q51: =IF(Table1[[#This Row],[Exit Date]]="", "Active","Exited") -> Active | R51: =IFERROR(DATEDIF(Table1[[#This Row],[Hire Date]],IF(Table1[[#This Row],[Exit Date]]="",TODAY(),Table1[[#This Row],[Exit Date]]),"Y"),"") -> 11 | S51: {=_xlfn.IFS(Table1[[#This Row],[Age]]<30,"Under 30",Table1[[#This Row],[Age]]<=40,"30-40",Table1[[#This Row],[Age]]<50,"41-50",TRUE,"50+")} -> 41-50
A52: E04917 | B52: Everleigh Washington | C52: HRIS Analyst | D52: Human Resources | E52: Research & Development | F52: Female | G52: Caucasian | H52: 64 | I52: 37184 | J52: 64057 | K52: 0 | L52: United States | M52: Phoenix | O52: =J52*K52 -> 0 | P52: =Table1[[#This Row],[Annual Salary]]+Table1[[#This Row],[Bonus Amount]] -> 64057 | Q52: =IF(Table1[[#This Row],[Exit Date]]="", "Active","Exited") -> Active | R52: =IFERROR(DATEDIF(Table1[[#This Row],[Hire Date]],IF(Table1[[#This Row],[Exit Date]]="",TODAY(),Table1[[#This Row],[Exit Date]]),"Y"),"") -> 24 | S52: {=_xlfn.IFS(Table1[[#This Row],[Age]]<30,"Under 30",Table1[[#This Row],[Age]]<=40,"30-40",Table1[[#This Row],[Age]]<50,"41-50",TRUE,"50+")} -> 50+
A53: E00415 | B53: Leilani Butler | C53: Analyst II | D53: Marketing | E53: Manufacturing | F53: Female | G53: Black | H53: 27 | I53: 44460 | J53: 68728 | K53: 0 | L53: United States | M53: Phoenix | O53: =J53*K53 -> 0 | P53: =Table1[[#This Row],[Annual Salary]]+Table1[[#This Row],[Bonus Amount]] -> 68728 | Q53: =IF(Table1[[#This Row],[Exit Date]]="", "Active","Exited") -> Active | R53: =IFERROR(DATEDIF(Table1[[#This Row],[Hire Date]],IF(Table1[[#This Row],[Exit Date]]="",TODAY(),Table1[[#This Row],[Exit Date]]),"Y"),"") -> 4 | S53: {=_xlfn.IFS(Table1[[#This Row],[Age]]<30,"Under 30",Table1[[#This Row],[Age]]<=40,"30-40",Table1[[#This Row],[Age]]<50,"41-50",TRUE,"50+")} -> Under 30
A54: E02862 | B54: Peyton Huang | C54: Sr. Manger | D54: IT | E54: Manufacturing | F54: Female | G54: Asian | H54: 25 | I54: 44379 | J54: 125633 | K54: 0.11 | L54: China | M54: Beijing | O54: =J54*K54 -> 13819.63 | P54: =Table1[[#This Row],[Annual Salary]]+Table1[[#This Row],[Bonus Amount]] -> 139452.63 | Q54: =IF(Table1[[#This Row],[Exit Date]]="", "Active","Exited") -> Active | R54: =IFERROR(DATEDIF(Table1[[#This Row],[Hire Date]],IF(Table1[[#This Row],[Exit Date]]="",TODAY(),Table1[[#This Row],[Exit Date]]),"Y"),"") -> 4 | S54: {=_xlfn.IFS(Table1[[#This Row],[Age]]<30,"Under 30",Table1[[#This Row],[Age]]<=40,"30-40",Table1[[#This Row],[Age]]<50,"41-50",TRUE,"50+")} -> Under 30
... A62: E00699 | B62: Ava Ayala | C62: Sr. Manger | D62: IT | E62: Corporate | F62: Female | G62: Latino | H62: 55 | I62: 38945 | J62: 159044 | K62: 0.1 | L62: Brazil | M62: Manaus | O62: =J62*K62 -> 15904.4 | P62: =Table1[[#This Row],[Annual Salary]]+Table1[[#This Row],[Bonus Amount]] -> 174948.4 | Q62: =IF(Table1[[#This Row],[Exit Date]]="", "Active","Exited") -> Active | R62: =IFERROR(DATEDIF(Table1[[#This Row],[Hire Date]],IF(Table1[[#This Row],[Exit Date]]="",TODAY(),Table1[[#This Row],[Exit Date]]),"Y"),"") -> 19 | S62: {=_xlfn.IFS(Table1[[#This Row],[Age]]<30,"Under 30",Table1[[#This Row],[Age]]<=40,"30-40",Table1[[#This Row],[Age]]<50,"41-50",TRUE,"50+")} -> 50+
A63: E00502 | B63: Natalia Salazar | C63: Sr. Analyst | D63: Accounting | E63: Manufacturing | F63: Female | G63: Latino | H63: 44 | I63: 43467 | J63: 74691 | K63: 0 | L63: Brazil | M63: Manaus | N63: 44020 | O63: =J63*K63 -> 0 | P63: =Table1[[#This Row],[Annual Salary]]+Table1[[#This Row],[Bonus Amount]] -> 74691 | Q63: =IF(Table1[[#This Row],[Exit Date]]="", "Active","Exited") -> Exited | R63: =IFERROR(DATEDIF(Table1[[#This Row],[Hire Date]],IF(Table1[[#This Row],[Exit Date]]="",TODAY(),Table1[[#This Row],[Exit Date]]),"Y"),"") -> 1 | S63: {=_xlfn.IFS(Table1[[#This Row],[Age]]<30,"Under 30",Table1[[#This Row],[Age]]<=40,"30-40",Table1[[#This Row],[Age]]<50,"41-50",TRUE,"50+")} -> 41-50
A64: E04000 | B64: Skylar Carrillo | C64: Engineering Manager | D64: Engineering | E64: Corporate | F64: Female | G64: Latino | H64: 44 | I64: 39800 | J64: 92753 | K64: 0.13 | L64: United States | M64: Austin | N64: 44371 | O64: =J64*K64 -> 12057.89 | P64: =Table1[[#This Row],[Annual Salary]]+Table1[[#This Row],[Bonus Amount]] -> 104810.89 | Q64: =IF(Table1[[#This Row],[Exit Date]]="", "Active","Exited") -> Exited | R64: =IFERROR(DATEDIF(Table1[[#This Row],[Hire Date]],IF(Table1[[#This Row],[Exit Date]]="",TODAY(),Table1[[#This Row],[Exit Date]]),"Y"),"") -> 12 | S64: {=_xlfn.IFS(Table1[[#This Row],[Age]]<30,"Under 30",Table1[[#This Row],[Age]]<=40,"30-40",Table1[[#This Row],[Age]]<50,"41-50",TRUE,"50+")} -> 41-50
A65: E02112 | B65: Christian Sanders | C65: Vice President | D65: Human Resources | E65: Speciality Products | F65: Male | G65: Black | H65: 45 | I65: 41493 | J65: 236946 | K65: 0.37 | L65: United States | M65: Seattle | O65: =J65*K65 -> 87670.02 | P65: =Table1[[#This Row],[Annual Salary]]+Table1[[#This Row],[Bonus Amount]] -> 324616.02 | Q65: =IF(Table1[[#This Row],[Exit Date]]="", "Active","Exited") -> Active | R65: =IFERROR(DATEDIF(Table1[[#This Row],[Hire Date]],IF(Table1[[#This Row],[Exit Date]]="",TODAY(),Table1[[#This Row],[Exit Date]]),"Y"),"") -> 12 | S65: {=_xlfn.IFS(Table1[[#This Row],[Age]]<30,"Under 30",Table1[[#This Row],[Age]]<=40,"30-40",Table1[[#This Row],[Age]]<50,"41-50",TRUE,"50+")} -> 41-50
A66: E03824 | B66: Penelope Coleman | C66: Analyst | D66: Finance | E66: Corporate | F66: Female | G66: Black | H66: 36 | I66: 44435 | J66: 48906 | K66: 0 | L66: United States | M66: Miami | O66: =J66*K66 -> 0 | P66: =Table1[[#This Row],[Annual Salary]]+Table1[[#This Row],[Bonus Amount]] -> 48906 | Q66: =IF(Table1[[#This Row],[Exit Date]]="", "Active","Exited") -> Active | R66: =IFERROR(DATEDIF(Table1[[#This Row],[Hire Date]],IF(Table1[[#This Row],[Exit Date]]="",TODAY(),Table1[[#This Row],[Exit Date]]),"Y"),"") -> 4 | S66: {=_xlfn.IFS(Table1[[#This Row],[Age]]<30,"Under 30",Table1[[#This Row],[Age]]<=40,"30-40",Table1[[#This Row],[Age]]<50,"41-50",TRUE,"50+")} -> 30-40
A67: E03906 | B67: Piper Richardson | C67: Sr. Analyst | D67: Sales | E67: Corporate | F67: Female | G67: Caucasian | H67: 38 | I67: 39474 | J67: 80024 | K67: 0 | L67: United States | M67: Columbus | O67: =J67*K67 -> 0 | P67: =Table1[[#This Row],[Annual Salary]]+Table1[[#This Row],[Bonus Amount]] -> 80024 | Q67: =IF(Table1[[#This Row],[Exit Date]]="", "Active","Exited") -> Active | R67: =IFERROR(DATEDIF(Table1[[#This Row],[Hire Date]],IF(Table1[[#This Row],[Exit Date]]="",TODAY(),Table1[[#This Row],[Exit Date]]),"Y"),"") -> 18 | S67: {=_xlfn.IFS(Table1[[#This Row],[Age]]<30,"Under 30",Table1[[#This Row],[Age]]<=40,"30-40",Table1[[#This Row],[Age]]<50,"41-50",TRUE,"50+")} -> 30-40
A68: E00436 | B68: Everly Walker | C68: HRIS Analyst | D68: Human Resources | E68: Speciality Products | F68: Female | G68: Caucasian | H68: 41 | I68: 40109 | J68: 54415 | K68: 0 | L68: United States | M68: Seattle | N68: 41661 | O68: =J68*K68 -> 0 | P68: =Table1[[#This Row],[Annual Salary]]+Table1[[#This Row],[Bonus Amount]] -> 54415 | Q68: =IF(Table1[[#This Row],[Exit Date]]="", "Active","Exited") -> Exited | R68: =IFERROR(DATEDIF(Table1[[#This Row],[Hire Date]],IF(Table1[[#This Row],[Exit Date]]="",TODAY(),Table1[[#This Row],[Exit Date]]),"Y"),"") -> 4 | S68: {=_xlfn.IFS(Table1[[#This Row],[Age]]<30,"Under 30",Table1[[#This Row],[Age]]<=40,"30-40",Table1[[#This Row],[Age]]<50,"41-50",TRUE,"50+")} -> 41-50
A69: E04798 | B69: Aurora Ali | C69: Manager | D69: Marketing | E69: Research & Development | F69: Female | G69: Asian | H69: 30 | I69: 42484 | J69: 120341 | K69: 0.07 | L69: United States | M69: Seattle | O69: =J69*K69 -> 8423.87 | P69: =Table1[[#This Row],[Annual Salary]]+Table1[[#This Row],[Bonus Amount]] -> 128764.87 | Q69: =IF(Table1[[#This Row],[Exit Date]]="", "Active","Exited") -> Active | R69: =IFERROR(DATEDIF(Table1[[#This Row],[Hire Date]],IF(Table1[[#This Row],[Exit Date]]="",TODAY(),Table1[[#This Row],[Exit Date]]),"Y"),"") -> 9 | S69: {=_xlfn.IFS(Table1[[#This Row],[Age]]<30,"Under 30",Table1[[#This Row],[Age]]<=40,"30-40",Table1[[#This Row],[Age]]<50,"41-50",TRUE,"50+")} -> 30-40
A70: E01249 | B70: Penelope Guerrero | C70: Vice President | D70: IT | E70: Speciality Products | F70: Female | G70: Latino | H70: 43 | I70: 40029 | J70: 208415 | K70: 0.35 | L70: United States | M70: Seattle | O70: =J70*K70 -> 72945.25 | P70: =Table1[[#This Row],[Annual Salary]]+Table1[[#This Row],[Bonus Amount]] -> 281360.25 | Q70: =IF(Table1[[#This Row],[Exit Date]]="", "Active","Exited") -> Active | R70: =IFERROR(DATEDIF(Table1[[#This Row],[Hire Date]],IF(Table1[[#This Row],[Exit Date]]="",TODAY(),Table1[[#This Row],[Exit Date]]),"Y"),"") -> 16 | S70: {=_xlfn.IFS(Table1[[#This Row],[Age]]<30,"Under 30",Table1[[#This Row],[Age]]<=40,"30-40",Table1[[#This Row],[Age]]<50,"41-50",TRUE,"50+")} -> 41-50
A71: E03349 | B71: Anna Mehta | C71: Cloud Infrastructure Architect | D71: IT | E71: Speciality Products | F71: Female | G71: Asian | H71: 32 | I71: 43835 | J71: 78844 | K71: 0 | L71: United States | M71: Seattle | O71: =J71*K71 -> 0 | P71: =Table1[[#This Row],[Annual Salary]]+Table1[[#This Row],[Bonus Amount]] -> 78844 | Q71: =IF(Table1[[#This Row],[Exit Date]]="", "Active","Exited") -> Active | R71: =IFERROR(DATEDIF(Table1[[#This Row],[Hire Date]],IF(Table1[[#This Row],[Exit Date]]="",TODAY(),Table1[[#This Row],[Exit Date]]),"Y"),"") -> 6 | S71: {=_xlfn.IFS(Table1[[#This Row],[Age]]<30,"Under 30",Table1[[#This Row],[Age]]<=40,"30-40",Table1[[#This Row],[Age]]<50,"41-50",TRUE,"50+")} -> 30-40
A72: E02966 | B72: William Foster | C72: Field Engineer | D72: Engineering | E72: Manufacturing | F72: Male | G72: Caucasian | H72: 58 | I72: 37399 | J72: 76354 | K72: 0 | L72: United States | M72: Phoenix | N72: 44465 | O72: =J72*K72 -> 0 | P72: =Table1[[#This Row],[Annual Salary]]+Table1[[#This Row],[Bonus Amount]] -> 76354 | Q72: =IF(Table1[[#This Row],[Exit Date]]="", "Active","Exited") -> Exited | R72: =IFERROR(DATEDIF(Table1[[#This Row],[Hire Date]],IF(Table1[[#This Row],[Exit Date]]="",TODAY(),Table1[[#This Row],[Exit Date]]),"Y"),"") -> 19 | S72: {=_xlfn.IFS(Table1[[#This Row],[Age]]<30,"Under 30",Table1[[#This Row],[Age]]<=40,"30-40",Table1[[#This Row],[Age]]<50,"41-50",TRUE,"50+")} -> 50+
A73: E01499 | B73: Jade Rojas | C73: Director | D73: Finance | E73: Speciality Products | F73: Female | G73: Latino | H73: 37 | I73: 43493 | J73: 165927 | K73: 0.2 | L73: United States | M73: Phoenix | O73: =J73*K73 -> 33185.4 | P73: =Table1[[#This Row],[Annual Salary]]+Table1[[#This Row],[Bonus Amount]] -> 199112.4 | Q73: =IF(Table1[[#This Row],[Exit Date]]="", "Active","Exited") -> Active | R73: =IFERROR(DATEDIF(Table1[[#This Row],[Hire Date]],IF(Table1[[#This Row],[Exit Date]]="",TODAY(),Table1[[#This Row],[Exit Date]]),"Y"),"") -> 7 | S73: {=_xlfn.IFS(Table1[[#This Row],[Age]]<30,"Under 30",Table1[[#This Row],[Age]]<=40,"30-40",Table1[[#This Row],[Age]]<50,"41-50",TRUE,"50+")} -> 30-40
A74: E00105 | B74: Isla Espinoza | C74: Manager | D74: Accounting | E74: Speciality Products | F74: Female | G74: Latino | H74: 38 | I74: 44516 | J74: 109812 | K74: 0.09 | L74: Brazil | M74: Manaus | O74: =J74*K74 -> 9883.08 | P74: =Table1[[#This Row],[Annual Salary]]+Table1[[#This Row],[Bonus Amount]] -> 119695.08 | Q74: =IF(Table1[[#This Row],[Exit Date]]="", "Active","Exited") -> Active | R74: =IFERROR(DATEDIF(Table1[[#This Row],[Hire Date]],IF(Table1[[#This Row],[Exit Date]]="",TODAY(),Table1[[#This Row],[Exit Date]]),"Y"),"") -> 4 | S74: {=_xlfn.IFS(Table1[[#This Row],[Age]]<30,"Under 30",Table1[[#This Row],[Age]]<=40,"30-40",Table1[[#This Row],[Age]]<50,"41-50",TRUE,"50+")} -> 30-40
A75: E00665 | B75: David Chu | C75: Controls Engineer | D75: Engineering | E75: Corporate | F75: Male | G75: Asian | H75: 55 | I75: 36041 | J75: 86299 | K75: 0 | L75: United States | M75: Seattle | O75: =J75*K75 -> 0 | P75: =Table1[[#This Row],[Annual Salary]]+Table1[[#This Row],[Bonus Amount]] -> 86299 | Q75: =IF(Table1[[#This Row],[Exit Date]]="", "Active","Exited") -> Active | R75: =IFERROR(DATEDIF(Table1[[#This Row],[Hire Date]],IF(Table1[[#This Row],[Exit Date]]="",TODAY(),Table1[[#This Row],[Exit Date]]),"Y"),"") -> 27 | S75: {=_xlfn.IFS(Table1[[#This Row],[Age]]<30,"Under 30",Table1[[#This Row],[Age]]<=40,"30-40",Table1[[#This Row],[Age]]<50,"41-50",TRUE,"50+")} -> 50+
A76: E00791 | B76: Thomas Padilla | C76: Vice President | D76: Marketing | E76: Research & Development | F76: Male | G76: Latino | H76: 57 | I76: 37828 | J76: 206624 | K76: 0.4 | L76: Brazil | M76: Sao Paulo | O76: =J76*K76 -> 82649.6 | P76: =Table1[[#This Row],[Annual Salary]]+Table1[[#This Row],[Bonus Amount]] -> 289273.6 | Q76: =IF(Table1[[#This Row],[Exit Date]]="", "Active","Exited") -> Active | R76: =IFERROR(DATEDIF(Table1[[#This Row],[Hire Date]],IF(Table1[[#This Row],[Exit Date]]="",TODAY(),Table1[[#This Row],[Exit Date]]),"Y"),"") -> 22 | S76: {=_xlfn.IFS(Table1[[#This Row],[Age]]<30,"Under 30",Table1[[#This Row],[Age]]<=40,"30-40",Table1[[#This Row],[Age]]<50,"41-50",TRUE,"50+")} -> 50+
A77: E01540 | B77: Miles Salazar | C77: IT Coordinator | D77: IT | E77: Manufacturing | F77: Male | G77: Latino | H77: 36 | I77: 40535 | J77: 53215 | K77: 0 | L77: Brazil | M77: Sao Paulo | N77: 41725 | O77: =J77*K77 -> 0 | P77: =Table1[[#This Row],[Annual Salary]]+Table1[[#This Row],[Bonus Amount]] -> 53215 | Q77: =IF(Table1[[#This Row],[Exit Date]]="", "Active","Exited") -> Exited | R77: =IFERROR(DATEDIF(Table1[[#This Row],[Hire Date]],IF(Table1[[#This Row],[Exit Date]]="",TODAY(),Table1[[#This Row],[Exit Date]]),"Y"),"") -> 3 | S77: {=_xlfn.IFS(Table1[[#This Row],[Age]]<30,"Under 30",Table1[[#This Row],[Age]]<=40,"30-40",Table1[[#This Row],[Age]]<50,"41-50",TRUE,"50+")} -> 30-40
A78: E04474 | B78: Mila Hong | C78: Test Engineer | D78: Engineering | E78: Research & Development | F78: Female | G78: Asian | H78: 30 | I78: 42877 | J78: 86858 | K78: 0 | L78: China | M78: Chongqing | N78: 43016 | O78: =J78*K78 -> 0 | P78: =Table1[[#This Row],[Annual Salary]]+Table1[[#This Row],[Bonus Amount]] -> 86858 | Q78: =IF(Table1[[#This Row],[Exit Date]]="", "Active","Exited") -> Exited | R78: =IFERROR(DATEDIF(Table1[[#This Row],[Hire Date]],IF(Table1[[#This Row],[Exit Date]]="",TODAY(),Table1[[#This Row],[Exit Date]]),"Y"),"") -> 0 | S78: {=_xlfn.IFS(Table1[[#This Row],[Age]]<30,"Under 30",Table1[[#This Row],[Age]]<=40,"30-40",Table1[[#This Row],[Age]]<50,"41-50",TRUE,"50+")} -> 30-40
A79: E03417 | B79: Benjamin Moua | C79: Computer Systems Manager | D79: IT | E79: Manufacturing | F79: Male | G79: Asian | H79: 40 | I79: 39265 | J79: 93971 | K79: 0.08 | L79: China | M79: Chongqing | O79: =J79*K79 -> 7517.68 | P79: =Table1[[#This Row],[Annual Salary]]+Table1[[#This Row],[Bonus Amount]] -> 101488.68 | Q79: =IF(Table1[[#This Row],[Exit Date]]="", "Active","Exited") -> Active | R79: =IFERROR(DATEDIF(Table1[[#This Row],[Hire Date]],IF(Table1[[#This Row],[Exit Date]]="",TODAY(),Table1[[#This Row],[Exit Date]]),"Y"),"") -> 18 | S79: {=_xlfn.IFS(Table1[[#This Row],[Age]]<30,"Under 30",Table1[[#This Row],[Age]]<=40,"30-40",Table1[[#This Row],[Age]]<50,"41-50",TRUE,"50+")} -> 30-40
A80: E00254 | B80: Samuel Morales | C80: Analyst II | D80: Finance | E80: Corporate | F80: Male | G80: Latino | H80: 34 | I80: 42182 | J80: 57008 | K80: 0 | L80: United States | M80: Phoenix | O80: =J80*K80 -> 0 | P80: =Table1[[#This Row],[Annual Salary]]+Table1[[#This Row],[Bonus Amount]] -> 57008 | Q80: =IF(Table1[[#This Row],[Exit Date]]="", "Active","Exited") -> Active | R80: =IFERROR(DATEDIF(Table1[[#This Row],[Hire Date]],IF(Table1[[#This Row],[Exit Date]]="",TODAY(),Table1[[#This Row],[Exit Date]]),"Y"),"") -> 10 | S80: {=_xlfn.IFS(Table1[[#This Row],[Age]]<30,"Under 30",Table1[[#This Row],[Age]]<=40,"30-40",Table1[[#This Row],[Age]]<50,"41-50",TRUE,"50+")} -> 30-40
A81: E02166 | B81: John Soto | C81: Sr. Manger | D81: Finance | E81: Manufacturing | F81: Male | G81: Latino | H81: 60 | I81: 42270 | J81: 141899 | K81: 0.15 | L81: United States | M81: Phoenix | O81: =J81*K81 -> 21284.85 | P81: =Table1[[#This Row],[Annual Salary]]+Table1[[#This Row],[Bonus Amount]] -> 163183.85 | Q81: =IF(Table1[[#This Row],[Exit Date]]="", "Active","Exited") -> Active | R81: =IFERROR(DATEDIF(Table1[[#This Row],[Hire Date]],IF(Table1[[#This Row],[Exit Date]]="",TODAY(),Table1[[#This Row],[Exit Date]]),"Y"),"") -> 10 | S81: {=_xlfn.IFS(Table1[[#This Row],[Age]]<30,"Under 30",Table1[[#This Row],[Age]]<=40,"30-40",Table1[[#This Row],[Age]]<50,"41-50",TRUE,"50+")} -> 50+
A82: E00935 | B82: Joseph Martin | C82: Analyst II | D82: Marketing | E82: Corporate | F82: Male | G82: Black | H82: 41 | I82: 42626 | J82: 64847 | K82: 0 | L82: United States | M82: Miami | O82: =J82*K82 -> 0 | P82: =Table1[[#This Row],[Annual Salary]]+Table1[[#This Row],[Bonus Amount]] -> 64847 | Q82: =IF(Table1[[#This Row],[Exit Date]]="", "Active","Exited") -> Active | R82: =IFERROR(DATEDIF(Table1[[#This Row],[Hire Date]],IF(Table1[[#This Row],[Exit Date]]="",TODAY(),Table1[[#This Row],[Exit Date]]),"Y"),"") -> 9 | S82: {=_xlfn.IFS(Table1[[#This Row],[Age]]<30,"Under 30",Table1[[#This Row],[Age]]<=40,"30-40",Table1[[#This Row],[Age]]<50,"41-50",TRUE,"50+")} -> 41-50
A83: E01525 | B83: Jose Ross | C83: Engineering Manager | D83: Engineering | E83: Research & Development | F83: Male | G83: Caucasian | H83: 53 | I83: 33702 | J83: 116878 | K83: 0.11 | L83: United States | M83: Miami | O83: =J83*K83 -> 12856.58 | P83: =Table1[[#This Row],[Annual Salary]]+Table1[[#This Row],[Bonus Amount]] -> 129734.58 | Q83: =IF(Table1[[#This Row],[Exit Date]]="", "Active","Exited") -> Active | R83: =IFERROR(DATEDIF(Table1[[#This Row],[Hire Date]],IF(Table1[[#This Row],[Exit Date]]="",TODAY(),Table1[[#This Row],[Exit Date]]),"Y"),"") -> 33 | S83: {=_xlfn.IFS(Table1[[#This Row],[Age]]<30,"Under 30",Table1[[#This Row],[Age]]<=40,"30-40",Table1[[#This Row],[Age]]<50,"41-50",TRUE,"50+")} -> 50+
A84: E00386 | B84: Parker James | C84: Quality Engineer | D84: Engineering | E84: Speciality Products | F84: Male | G84: Black | H84: 45 | I84: 38388 | J84: 70505 | K84: 0 | L84: United States | M84: Austin | O84: =J84*K84 -> 0 | P84: =Table1[[#This Row],[Annual Salary]]+Table1[[#This Row],[Bonus Amount]] -> 70505 | Q84: =IF(Table1[[#This Row],[Exit Date]]="", "Active","Exited") -> Active | R84: =IFERROR(DATEDIF(Table1[[#This Row],[Hire Date]],IF(Table1[[#This Row],[Exit Date]]="",TODAY(),Table1[[#This Row],[Exit Date]]),"Y"),"") -> 21 | S84: {=_xlfn.IFS(Table1[[#This Row],[Age]]<30,"Under 30",Table1[[#This Row],[Age]]<=40,"30-40",Table1[[#This Row],[Age]]<50,"41-50",TRUE,"50+")} -> 41-50
A85: E00416 | B85: Everleigh Fernandez | C85: Director | D85: Engineering | E85: Research & Development | F85: Female | G85: Latino | H85: 30 | I85: 42512 | J85: 189702 | K85: 0.28 | L85: Brazil | M85: Manaus | N85: 44186 | O85: =J85*K85 -> 53116.56 | P85: =Table1[[#This Row],[Annual Salary]]+Table1[[#This Row],[Bonus Amount]] -> 242818.56 | Q85: =IF(Table1[[#This Row],[Exit Date]]="", "Active","Exited") -> Exited | R85: =IFERROR(DATEDIF(Table1[[#This Row],[Hire Date]],IF(Table1[[#This Row],[Exit Date]]="",TODAY(),Table1[[#This Row],[Exit Date]]),"Y"),"") -> 4 | S85: {=_xlfn.IFS(Table1[[#This Row],[Age]]<30,"Under 30",Table1[[#This Row],[Age]]<=40,"30-40",Table1[[#This Row],[Age]]<50,"41-50",TRUE,"50+")} -> 30-40
A86: E03383 | B86: Lincoln Hall | C86: Director | D86: Accounting | E86: Speciality Products | F86: Male | G86: Caucasian | H86: 26 | I86: 44040 | J86: 180664 | K86: 0.27 | L86: United States | M86: Chicago | O86: =J86*K86 -> 48779.28 | P86: =Table1[[#This Row],[Annual Salary]]+Table1[[#This Row],[Bonus Amount]] -> 229443.28 | Q86: =IF(Table1[[#This Row],[Exit Date]]="", "Active","Exited") -> Active | R86: =IFERROR(DATEDIF(Table1[[#This Row],[Hire Date]],IF(Table1[[#This Row],[Exit Date]]="",TODAY(),Table1[[#This Row],[Exit Date]]),"Y"),"") -> 5 | S86: {=_xlfn.IFS(Table1[[#This Row],[Age]]<30,"Under 30",Table1[[#This Row],[Age]]<=40,"30-40",Table1[[#This Row],[Age]]<50,"41-50",TRUE,"50+")} -> Under 30
A87: E01516 | B87: Willow Mai | C87: Business Partner | D87: Human Resources | E87: Manufacturing | F87: Female | G87: Asian | H87: 45 | I87: 37972 | J87: 48345 | K87: 0 | L87: China | M87: Chengdu | O87: =J87*K87 -> 0 | P87: =Table1[[#This Row],[Annual Salary]]+Table1[[#This Row],[Bonus Amount]] -> 48345 | Q87: =IF(Table1[[#This Row],[Exit Date]]="", "Active","Exited") -> Active | R87: =IFERROR(DATEDIF(Table1[[#This Row],[Hire Date]],IF(Table1[[#This Row],[Exit Date]]="",TODAY(),Table1[[#This Row],[Exit Date]]),"Y"),"") -> 22 | S87: {=_xlfn.IFS(Table1[[#This Row],[Age]]<30,"Under 30",Table1[[#This Row],[Age]]<=40,"30-40",Table1[[#This Row],[Age]]<50,"41-50",TRUE,"50+")} -> 41-50
A88: E01234 | B88: Jack Cheng | C88: Director | D88: Human Resources | E88: Manufacturing | F88: Male | G88: Asian | H88: 42 | I88: 41655 | J88: 152214 | K88: 0.3 | L88: China | M88: Beijing | O88: =J88*K88 -> 45664.2 | P88: =Table1[[#This Row],[Annual Salary]]+Table1[[#This Row],[Bonus Amount]] -> 197878.2 | Q88: =IF(Table1[[#This Row],[Exit Date]]="", "Active","Exited") -> Active | R88: =IFERROR(DATEDIF(Table1[[#This Row],[Hire Date]],IF(Table1[[#This Row],[Exit Date]]="",TODAY(),Table1[[#This Row],[Exit Date]]),"Y"),"") -> 12 | S88: {=_xlfn.IFS(Table1[[#This Row],[Age]]<30,"Under 30",Table1[[#This Row],[Age]]<=40,"30-40",Table1[[#This Row],[Age]]<50,"41-50",TRUE,"50+")} -> 41-50
A89: E03440 | B89: Genesis Navarro | C89: Cloud Infrastructure Architect | D89: IT | E89: Corporate | F89: Female | G89: Latino | H89: 41 | I89: 39931 | J89: 69803 | K89: 0 | L89: Brazil | M89: Manaus | O89: =J89*K89 -> 0 | P89: =Table1[[#This Row],[Annual Salary]]+Table1[[#This Row],[Bonus Amount]] -> 69803 | Q89: =IF(Table1[[#This Row],[Exit Date]]="", "Active","Exited") -> Active | R89: =IFERROR(DATEDIF(Table1[[#This Row],[Hire Date]],IF(Table1[[#This Row],[Exit Date]]="",TODAY(),Table1[[#This Row],[Exit Date]]),"Y"),"") -> 16 | S89: {=_xlfn.IFS(Table1[[#This Row],[Age]]<30,"Under 30",Table1[[#This Row],[Age]]<=40,"30-40",Table1[[#This Row],[Age]]<50,"41-50",TRUE,"50+")} -> 41-50
A90: E00431 | B90: Eliza Hernandez | C90: Network Architect | D90: IT | E90: Corporate | F90: Female | G90: Latino | H90: 48 | I90: 43650 | J90: 76588 | K90: 0 | L90: Brazil | M90: Rio de Janerio | O90: =J90*K90 -> 0 | P90: =Table1[[#This Row],[Annual Salary]]+Table1[[#This Row],[Bonus Amount]] -> 76588 | Q90: =IF(Table1[[#This Row],[Exit Date]]="", "Active","Exited") -> Active | R90: =IFERROR(DATEDIF(Table1[[#This Row],[Hire Date]],IF(Table1[[#This Row],[Exit Date]]="",TODAY(),Table1[[#This Row],[Exit Date]]),"Y"),"") -> 6 | S90: {=_xlfn.IFS(Table1[[#This Row],[Age]]<30,"Under 30",Table1[[#This Row],[Age]]<=40,"30-40",Table1[[#This Row],[Age]]<50,"41-50",TRUE,"50+")} -> 41-50
A91: E01258 | B91: Gabriel Brooks | C91: Network Engineer | D91: IT | E91: Manufacturing | F91: Male | G91: Caucasian | H91: 29 | I91: 43444 | J91: 84596 | K91: 0 | L91: United States | M91: Miami | O91: =J91*K91 -> 0 | P91: =Table1[[#This Row],[Annual Salary]]+Table1[[#This Row],[Bonus Amount]] -> 84596 | Q91: =IF(Table1[[#This Row],[Exit Date]]="", "Active","Exited") -> Active | R91: =IFERROR(DATEDIF(Table1[[#This Row],[Hire Date]],IF(Table1[[#This Row],[Exit Date]]="",TODAY(),Table1[[#This Row],[Exit Date]]),"Y"),"") -> 7 | S91: {=_xlfn.IFS(Table1[[#This Row],[Age]]<30,"Under 30",Table1[[#This Row],[Age]]<=40,"30-40",Table1[[#This Row],[Age]]<50,"41-50",TRUE,"50+")} -> Under 30
A92: E00440 | B92: Jack Huynh | C92: Manager | D92: Marketing | E92: Research & Development | F92: Male | G92: Asian | H92: 27 | I92: 43368 | J92: 114441 | K92: 0.1 | L92: China | M92: Chongqing | N92: 43821 | O92: =J92*K92 -> 11444.1 | P92: =Table1[[#This Row],[Annual Salary]]+Table1[[#This Row],[Bonus Amount]] -> 125885.1 | Q92: =IF(Table1[[#This Row],[Exit Date]]="", "Active","Exited") -> Exited | R92: =IFERROR(DATEDIF(Table1[[#This Row],[Hire Date]],IF(Table1[[#This Row],[Exit Date]]="",TODAY(),Table1[[#This Row],[Exit Date]]),"Y"),"") -> 1 | S92: {=_xlfn.IFS(Table1[[#This Row],[Age]]<30,"Under 30",Table1[[#This Row],[Age]]<=40,"30-40",Table1[[#This Row],[Age]]<50,"41-50",TRUE,"50+")} -> Under 30
A93: E00595 | B93: Everly Chow | C93: Sr. Manger | D93: Finance | E93: Speciality Products | F93: Female | G93: Asian | H93: 33 | I93: 43211 | J93: 140402 | K93: 0.15 | L93: China | M93: Beijing | O93: =J93*K93 -> 21060.3 | P93: =Table1[[#This Row],[Annual Salary]]+Table1[[#This Row],[Bonus Amount]] -> 161462.3 | Q93: =IF(Table1[[#This Row],[Exit Date]]="", "Active","Exited") -> Active | R93: =IFERROR(DATEDIF(Table1[[#This Row],[Hire Date]],IF(Table1[[#This Row],[Exit Date]]="",TODAY(),Table1[[#This Row],[Exit Date]]),"Y"),"") -> 7 | S93: {=_xlfn.IFS(Table1[[#This Row],[Age]]<30,"Under 30",Table1[[#This Row],[Age]]<=40,"30-40",Table1[[#This Row],[Age]]<50,"41-50",TRUE,"50+")} -> 30-40
A94: E00972 | B94: Amelia Salazar | C94: Analyst II | D94: Finance | E94: Corporate | F94: Female | G94: Latino | H94: 26 | I94: 43578 | J94: 59817 | K94: 0 | L94: Brazil | M94: Sao Paulo | O94: =J94*K94 -> 0 | P94: =Table1[[#This Row],[Annual Salary]]+Table1[[#This Row],[Bonus Amount]] -> 59817 | Q94: =IF(Table1[[#This Row],[Exit Date]]="", "Active","Exited") -> Active | R94: =IFERROR(DATEDIF(Table1[[#This Row],[Hire Date]],IF(Table1[[#This Row],[Exit Date]]="",TODAY(),Table1[[#This Row],[Exit Date]]),"Y"),"") -> 6 | S94: {=_xlfn.IFS(Table1[[#This Row],[Age]]<30,"Under 30",Table1[[#This Row],[Age]]<=40,"30-40",Table1[[#This Row],[Age]]<50,"41-50",TRUE,"50+")} -> Under 30
A95: E04562 | B95: Xavier Zheng | C95: Account Representative | D95: Sales | E95: Manufacturing | F95: Male | G95: Asian | H95: 31 | I95: 42938 | J95: 55854 | K95: 0 | L95: United States | M95: Austin | O95: =J95*K95 -> 0 | P95: =Table1[[#This Row],[Annual Salary]]+Table1[[#This Row],[Bonus Amount]] -> 55854 | Q95: =IF(Table1[[#This Row],[Exit Date]]="", "Active","Exited") -> Active | R95: =IFERROR(DATEDIF(Table1[[#This Row],[Hire Date]],IF(Table1[[#This Row],[Exit Date]]="",TODAY(),Table1[[#This Row],[Exit Date]]),"Y"),"") -> 8 | S95: {=_xlfn.IFS(Table1[[#This Row],[Age]]<30,"Under 30",Table1[[#This Row],[Age]]<=40,"30-40",Table1[[#This Row],[Age]]<50,"41-50",TRUE,"50+")} -> 30-40
A96: E02802 | B96: Matthew Chau | C96: Sr. Business Partner | D96: Human Resources | E96: Research & Development | F96: Male | G96: Asian | H96: 53 | I96: 37576 | J96: 95998 | K96: 0 | L96: United States | M96: Seattle | O96: =J96*K96 -> 0 | P96: =Table1[[#This Row],[Annual Salary]]+Table1[[#This Row],[Bonus Amount]] -> 95998 | Q96: =IF(Table1[[#This Row],[Exit Date]]="", "Active","Exited") -> Active | R96: =IFERROR(DATEDIF(Table1[[#This Row],[Hire Date]],IF(Table1[[#This Row],[Exit Date]]="",TODAY(),Table1[[#This Row],[Exit Date]]),"Y"),"") -> 23 | S96: {=_xlfn.IFS(Table1[[#This Row],[Age]]<30,"Under 30",Table1[[#This Row],[Age]]<=40,"30-40",Table1[[#This Row],[Age]]<50,"41-50",TRUE,"50+")} -> 50+
A97: E01427 | B97: Mia Cheng | C97: Sr. Manger | D97: Sales | E97: Manufacturing | F97: Female | G97: Asian | H97: 34 | I97: 42116 | J97: 154941 | K97: 0.13 | L97: United States | M97: Phoenix | O97: =J97*K97 -> 20142.33 | P97: =Table1[[#This Row],[Annual Salary]]+Table1[[#This Row],[Bonus Amount]] -> 175083.33 | Q97: =IF(Table1[[#This Row],[Exit Date]]="", "Active","Exited") -> Active | R97: =IFERROR(DATEDIF(Table1[[#This Row],[Hire Date]],IF(Table1[[#This Row],[Exit Date]]="",TODAY(),Table1[[#This Row],[Exit Date]]),"Y"),"") -> 10 | S97: {=_xlfn.IFS(Table1[[#This Row],[Age]]<30,"Under 30",Table1[[#This Row],[Age]]<=40,"30-40",Table1[[#This Row],[Age]]<50,"41-50",TRUE,"50+")} -> 30-40
A98: E04568 | B98: Rylee Yu | C98: Vice President | D98: Finance | E98: Speciality Products | F98: Female | G98: Asian | H98: 54 | I98: 40734 | J98: 247022 | K98: 0.3 | L98: China | M98: Beijing | O98: =J98*K98 -> 74106.6 | P98: =Table1[[#This Row],[Annual Salary]]+Table1[[#This Row],[Bonus Amount]] -> 321128.6 | Q98: =IF(Table1[[#This Row],[Exit Date]]="", "Active","Exited") -> Active | R98: =IFERROR(DATEDIF(Table1[[#This Row],[Hire Date]],IF(Table1[[#This Row],[Exit Date]]="",TODAY(),Table1[[#This Row],[Exit Date]]),"Y"),"") -> 14 | S98: {=_xlfn.IFS(Table1[[#This Row],[Age]]<30,"Under 30",Table1[[#This Row],[Age]]<=40,"30-40",Table1[[#This Row],[Age]]<50,"41-50",TRUE,"50+")} -> 50+
A99: E04931 | B99: Zoe Romero | C99: Network Architect | D99: IT | E99: Manufacturing | F99: Female | G99: Latino | H99: 32 | I99: 44474 | J99: 88072 | K99: 0 | L99: Brazil | M99: Sao Paulo | O99: =J99*K99 -> 0 | P99: =Table1[[#This Row],[Annual Salary]]+Table1[[#This Row],[Bonus Amount]] -> 88072 | Q99: =IF(Table1[[#This Row],[Exit Date]]="", "Active","Exited") -> Active | R99: =IFERROR(DATEDIF(Table1[[#This Row],[Hire Date]],IF(Table1[[#This Row],[Exit Date]]="",TODAY(),Table1[[#This Row],[Exit Date]]),"Y"),"") -> 4 | S99: {=_xlfn.IFS(Table1[[#This Row],[Age]]<30,"Under 30",Table1[[#This Row],[Age]]<=40,"30-40",Table1[[#This Row],[Age]]<50,"41-50",TRUE,"50+")} -> 30-40
A100: E00443 | B100: Nolan Bui | C100: Computer Systems Manager | D100: IT | E100: Research & Development | F100: Male | G100: Asian | H100: 28 | I100: 43977 | J100: 67925 | K100: 0.08 | L100: China | M100: Shanghai | O100: =J100*K100 -> 5434 | P100: =Table1[[#This Row],[Annual Salary]]+Table1[[#This Row],[Bonus Amount]] -> 73359 | Q100: =IF(Table1[[#This Row],[Exit Date]]="", "Active","Exited") -> Active | R100: =IFERROR(DATEDIF(Table1[[#This Row],[Hire Date]],IF(Table1[[#This Row],[Exit Date]]="",TODAY(),Table1[[#This Row],[Exit Date]]),"Y"),"") -> 5 | S100: {=_xlfn.IFS(Table1[[#This Row],[Age]]<30,"Under 30",Table1[[#This Row],[Age]]<=40,"30-40",Table1[[#This Row],[Age]]<50,"41-50",TRUE,"50+")} -> Under 30
A101: E03890 | B101: Nevaeh Jones | C101: Vice President | D101: Sales | E101: Manufacturing | F101: Female | G101: Caucasian | H101: 31 | I101: 44063 | J101: 219693 | K101: 0.3 | L101: United States | M101: Austin | O101: =J101*K101 -> 65907.9 | P101: =Table1[[#This Row],[Annual Salary]]+Table1[[#This Row],[Bonus Amount]] -> 285600.9 | Q101: =IF(Table1[[#This Row],[Exit Date]]="", "Active","Exited") -> Active | R101: =IFERROR(DATEDIF(Table1[[#This Row],[Hire Date]],IF(Table1[[#This Row],[Exit Date]]="",TODAY(),Table1[[#This Row],[Exit Date]]),"Y"),"") -> 5 | S101: {=_xlfn.IFS(Table1[[#This Row],[Age]]<30,"Under 30",Table1[[#This Row],[Age]]<=40,"30-40",Table1[[#This Row],[Age]]<50,"41-50",TRUE,"50+")} -> 30-40
A102: E01194 | B102: Samantha Adams | C102: Test Engineer | D102: Engineering | E102: Research & Development | F102: Female | G102: Caucasian | H102: 45 | I102: 41386 | J102: 61773 | K102: 0 | L102: United States | M102: Seattle | O102: =J102*K102 -> 0 | P102: =Table1[[#This Row],[Annual Salary]]+Table1[[#This Row],[Bonus Amount]] -> 61773 | Q102: =IF(Table1[[#This Row],[Exit Date]]="", "Active","Exited") -> Active | R102: =IFERROR(DATEDIF(Table1[[#This Row],[Hire Date]],IF(Table1[[#This Row],[Exit Date]]="",TODAY(),Table1[[#This Row],[Exit Date]]),"Y"),"") -> 12 | S102: {=_xlfn.IFS(Table1[[#This Row],[Age]]<30,"Under 30",Table1[[#This Row],[Age]]<=40,"30-40",Table1[[#This Row],[Age]]<50,"41-50",TRUE,"50+")} -> 41-50
A103: E02875 | B103: Madeline Shin | C103: Computer Systems Manager | D103: IT | E103: Speciality Products | F103: Female | G103: Asian | H103: 48 | I103: 39091 | J103: 74546 | K103: 0.09 | L103: United States | M103: Seattle | O103: =J103*K103 -> 6709.14 | P103: =Table1[[#This Row],[Annual Salary]]+Table1[[#This Row],[Bonus Amount]] -> 81255.14 | Q103: =IF(Table1[[#This Row],[Exit Date]]="", "Active","Exited") -> Active | R103: =IFERROR(DATEDIF(Table1[[#This Row],[Hire Date]],IF(Table1[[#This Row],[Exit Date]]="",TODAY(),Table1[[#This Row],[Exit Date]]),"Y"),"") -> 19 | S103: {=_xlfn.IFS(Table1[[#This Row],[Age]]<30,"Under 30",Table1[[#This Row],[Age]]<=40,"30-40",Table1[[#This Row],[Age]]<50,"41-50",TRUE,"50+")} -> 41-50
A104: E04959 | B104: Noah King | C104: Development Engineer | D104: Engineering | E104: Speciality Products | F104: Male | G104: Black | H104: 56 | I104: 42031 | J104: 62575 | K104: 0 | L104: United States | M104: Miami | O104: =J104*K104 -> 0 | P104: =Table1[[#This Row],[Annual Salary]]+Table1[[#This Row],[Bonus Amount]] -> 62575 | Q104: =IF(Table1[[#This Row],[Exit Date]]="", "Active","Exited") -> Active | R104: =IFERROR(DATEDIF(Table1[[#This Row],[Hire Date]],IF(Table1[[#This Row],[Exit Date]]="",TODAY(),Table1[[#This Row],[Exit Date]]),"Y"),"") -> 11 | S104: {=_xlfn.IFS(Table1[[#This Row],[Age]]<30,"Under 30",Table1[[#This Row],[Age]]<=40,"30-40",Table1[[#This Row],[Age]]<50,"41-50",TRUE,"50+")} -> 50+
A105: E03816 | B105: Leilani Chow | C105: Director | D105: Human Resources | E105: Corporate | F105: Female | G105: Asian | H105: 27 | I105: 44250 | J105: 199041 | K105: 0.16 | L105: China | M105: Beijing | O105: =J105*K105 -> 31846.56 | P105: =Table1[[#This Row],[Annual Salary]]+Table1[[#This Row],[Bonus Amount]] -> 230887.56 | Q105: =IF(Table1[[#This Row],[Exit Date]]="", "Active","Exited") -> Active | R105: =IFERROR(DATEDIF(Table1[[#This Row],[Hire Date]],IF(Table1[[#This Row],[Exit Date]]="",TODAY(),Table1[[#This Row],[Exit Date]]),"Y"),"") -> 5 | S105: {=_xlfn.IFS(Table1[[#This Row],[Age]]<30,"Under 30",Table1[[#This Row],[Age]]<=40,"30-40",Table1[[#This Row],[Age]]<50,"41-50",TRUE,"50+")} -> Under 30
A106: E01261 | B106: Connor Simmons | C106: Analyst II | D106: Accounting | E106: Speciality Products | F106: Male | G106: Caucasian | H106: 55 | I106: 39177 | J106: 52310 | K106: 0 | L106: United States | M106: Miami | N106: 43385 | O106: =J106*K106 -> 0 | P106: =Table1[[#This Row],[Annual Salary]]+Table1[[#This Row],[Bonus Amount]] -> 52310 | Q106: =IF(Table1[[#This Row],[Exit Date]]="", "Active","Exited") -> Exited | R106: =IFERROR(DATEDIF(Table1[[#This Row],[Hire Date]],IF(Table1[[#This Row],[Exit Date]]="",TODAY(),Table1[[#This Row],[Exit Date]]),"Y"),"") -> 11 | S106: {=_xlfn.IFS(Table1[[#This Row],[Age]]<30,"Under 30",Table1[[#This Row],[Age]]<=40,"30-40",Table1[[#This Row],[Age]]<50,"41-50",TRUE,"50+")} -> 50+
A107: E03612 | B107: Grayson Cooper | C107: Sr. Manger | D107: Finance | E107: Speciality Products | F107: Male | G107: Black | H107: 64 | I107: 41454 | J107: 159571 | K107: 0.1 | L107: United States | M107: Columbus | O107: =J107*K107 -> 15957.1 | P107: =Table1[[#This Row],[Annual Salary]]+Table1[[#This Row],[Bonus Amount]] -> 175528.1 | Q107: =IF(Table1[[#This Row],[Exit Date]]="", "Active","Exited") -> Active | R107: =IFERROR(DATEDIF(Table1[[#This Row],[Hire Date]],IF(Table1[[#This Row],[Exit Date]]="",TODAY(),Table1[[#This Row],[Exit Date]]),"Y"),"") -> 12 | S107: {=_xlfn.IFS(Table1[[#This Row],[Age]]<30,"Under 30",Table1[[#This Row],[Age]]<=40,"30-40",Table1[[#This Row],[Age]]<50,"41-50",TRUE,"50+")} -> 50+
A108: E01388 | B108: Ivy Soto | C108: Field Engineer | D108: Engineering | E108: Research & Development | F108: Female | G108: Latino | H108: 50 | I108: 35726 | J108: 91763 | K108: 0 | L108: United States | M108: Austin | O108: =J108*K108 -> 0 | P108: =Table1[[#This Row],[Annual Salary]]+Table1[[#This Row],[Bonus Amount]] -> 91763 | Q108: =IF(Table1[[#This Row],[Exit Date]]="", "Active","Exited") -> Active | R108: =IFERROR(DATEDIF(Table1[[#This Row],[Hire Date]],IF(Table1[[#This Row],[Exit Date]]="",TODAY(),Table1[[#This Row],[Exit Date]]),"Y"),"") -> 28 | S108: {=_xlfn.IFS(Table1[[#This Row],[Age]]<30,"Under 30",Table1[[#This Row],[Age]]<=40,"30-40",Table1[[#This Row],[Age]]<50,"41-50",TRUE,"50+")} -> 50+
A109: E03875 | B109: Aurora Simmons | C109: Development Engineer | D109: Engineering | E109: Corporate | F109: Female | G109: Caucasian | H109: 51 | I109: 35055 | J109: 96475 | K109: 0 | L109: United States | M109: Austin | O109: =J109*K109 -> 0 | P109: =Table1[[#This Row],[Annual Salary]]+Table1[[#This Row],[Bonus Amount]] -> 96475 | Q109: =IF(Table1[[#This Row],[Exit Date]]="", "Active","Exited") -> Active | R109: =IFERROR(DATEDIF(Table1[[#This Row],[Hire Date]],IF(Table1[[#This Row],[Exit Date]]="",TODAY(),Table1[[#This Row],[Exit Date]]),"Y"),"") -> 30 | S109: {=_xlfn.IFS(Table1[[#This Row],[Age]]<30,"Under 30",Table1[[#This Row],[Age]]<=40,"30-40",Table1[[#This Row],[Age]]<50,"41-50",TRUE,"50+")} -> 50+
A110: E04413 | B110: Andrew Thomas | C110: Controls Engineer | D110: Engineering | E110: Manufacturing | F110: Male | G110: Caucasian | H110: 36 | I110: 42706 | J110: 113781 | K110: 0 | L110: United States | M110: Columbus | O110: =J110*K110 -> 0 | P110: =Table1[[#This Row],[Annual Salary]]+Table1[[#This Row],[Bonus Amount]] -> 113781 | Q110: =IF(Table1[[#This Row],[Exit Date]]="", "Active","Exited") -> Active | R110: =IFERROR(DATEDIF(Table1[[#This Row],[Hire Date]],IF(Table1[[#This Row],[Exit Date]]="",TODAY(),Table1[[#This Row],[Exit Date]]),"Y"),"") -> 9 | S110: {=_xlfn.IFS(Table1[[#This Row],[Age]]<30,"Under 30",Table1[[#This Row],[Age]]<=40,"30-40",Table1[[#This Row],[Age]]<50,"41-50",TRUE,"50+")} -> 30-40
A111: E00691 | B111: Ezekiel Desai | C111: Director | D111: Finance | E111: Research & Development | F111: Male | G111: Asian | H111: 42 | I111: 37636 | J111: 166599 | K111: 0.26 | L111: United States | M111: Seattle | O111: =J111*K111 -> 43315.74 | P111: =Table1[[#This Row],[Annual Salary]]+Table1[[#This Row],[Bonus Amount]] -> 209914.74 | Q111: =IF(Table1[[#This Row],[Exit Date]]="", "Active","Exited") -> Active | R111: =IFERROR(DATEDIF(Table1[[#This Row],[Hire Date]],IF(Table1[[#This Row],[Exit Date]]="",TODAY(),Table1[[#This Row],[Exit Date]]),"Y"),"") -> 23 | S111: {=_xlfn.IFS(Table1[[#This Row],[Age]]<30,"Under 30",Table1[[#This Row],[Age]]<=40,"30-40",Table1[[#This Row],[Age]]<50,"41-50",TRUE,"50+")} -> 41-50
A112: E03047 | B112: Gabriella Gupta | C112: Sr. Account Representative | D112: Sales | E112: Corporate | F112: Female | G112: Asian | H112: 41 | I112: 38398 | J112: 95372 | K112: 0 | L112: China | M112: Shanghai | O112: =J112*K112 -> 0 | P112: =Table1[[#This Row],[Annual Salary]]+Table1[[#This Row],[Bonus Amount]] -> 95372 | Q112: =IF(Table1[[#This Row],[Exit Date]]="", "Active","Exited") -> Active | R112: =IFERROR(DATEDIF(Table1[[#This Row],[Hire Date]],IF(Table1[[#This Row],[Exit Date]]="",TODAY(),Table1[[#This Row],[Exit Date]]),"Y"),"") -> 21 | S112: {=_xlfn.IFS(Table1[[#This Row],[Age]]<30,"Under 30",Table1[[#This Row],[Age]]<=40,"30-40",Table1[[#This Row],[Age]]<50,"41-50",TRUE,"50+")} -> 41-50
A113: E04903 | B113: Skylar Liu | C113: Director | D113: IT | E113: Research & Development | F113: Female | G113: Asian | H113: 29 | I113: 44052 | J113: 161203 | K113: 0.15 | L113: China | M113: Chengdu | O113: =J113*K113 -> 24180.45 | P113: =Table1[[#This Row],[Annual Salary]]+Table1[[#This Row],[Bonus Amount]] -> 185383.45 | Q113: =IF(Table1[[#This Row],[Exit Date]]="", "Active","Exited") -> Active | R113: =IFERROR(DATEDIF(Table1[[#This Row],[Hire Date]],IF(Table1[[#This Row],[Exit Date]]="",TODAY(),Table1[[#This Row],[Exit Date]]),"Y"),"") -> 5 | S113: {=_xlfn.IFS(Table1[[#This Row],[Age]]<30,"Under 30",Table1[[#This Row],[Age]]<=40,"30-40",Table1[[#This Row],[Age]]<50,"41-50",TRUE,"50+")} -> Under 30
A114: E04735 | B114: Nova Coleman | C114: System Administrator | D114: IT | E114: Manufacturing | F114: Female | G114: Caucasian | H114: 44 | I114: 39064 | J114: 74738 | K114: 0 | L114: United States | M114: Miami | O114: =J114*K114 -> 0 | P114: =Table1[[#This Row],[Annual Salary]]+Table1[[#This Row],[Bonus Amount]] -> 74738 | Q114: =IF(Table1[[#This Row],[Exit Date]]="", "Active","Exited") -> Active | R114: =IFERROR(DATEDIF(Table1[[#This Row],[Hire Date]],IF(Table1[[#This Row],[Exit Date]]="",TODAY(),Table1[[#This Row],[Exit Date]]),"Y"),"") -> 19 | S114: {=_xlfn.IFS(Table1[[#This Row],[Age]]<30,"Under 30",Table1[[#This Row],[Age]]<=40,"30-40",Table1[[#This Row],[Age]]<50,"41-50",TRUE,"50+")} -> 41-50
A115: E02850 | B115: Evelyn Dinh | C115: Director | D115: Sales | E115: Research & Development | F115: Female | G115: Asian | H115: 41 | I115: 43322 | J115: 171173 | K115: 0.21 | L115: United States | M115: Columbus | O115: =J115*K115 -> 35946.33 | P115: =Table1[[#This Row],[Annual Salary]]+Table1[[#This Row],[Bonus Amount]] -> 207119.33 | Q115: =IF(Table1[[#This Row],[Exit Date]]="", "Active","Exited") -> Active | R115: =IFERROR(DATEDIF(Table1[[#This Row],[Hire Date]],IF(Table1[[#This Row],[Exit Date]]="",TODAY(),Table1[[#This Row],[Exit Date]]),"Y"),"") -> 7 | S115: {=_xlfn.IFS(Table1[[#This Row],[Age]]<30,"Under 30",Table1[[#This Row],[Age]]<=40,"30-40",Table1[[#This Row],[Age]]<50,"41-50",TRUE,"50+")} -> 41-50
A116: E03583 | B116: Brooks Marquez | C116: Vice President | D116: Sales | E116: Corporate | F116: Male | G116: Latino | H116: 61 | I116: 43732 | J116: 201464 | K116: 0.37 | L116: United States | M116: Chicago | O116: =J116*K116 -> 74541.68 | P116: =Table1[[#This Row],[Annual Salary]]+Table1[[#This Row],[Bonus Amount]] -> 276005.68 | Q116: =IF(Table1[[#This Row],[Exit Date]]="", "Active","Exited") -> Active | R116: =IFERROR(DATEDIF(Table1[[#This Row],[Hire Date]],IF(Table1[[#This Row],[Exit Date]]="",TODAY(),Table1[[#This Row],[Exit Date]]),"Y"),"") -> 6 | S116: {=_xlfn.IFS(Table1[[#This Row],[Age]]<30,"Under 30",Table1[[#This Row],[Age]]<=40,"30-40",Table1[[#This Row],[Age]]<50,"41-50",TRUE,"50+")} -> 50+
A117: E02017 | B117: Connor Joseph | C117: Director | D117: Human Resources | E117: Corporate | F117: Male | G117: Caucasian | H117: 50 | I117: 35998 | J117: 174895 | K117: 0.15 | L117: United States | M117: Chicago | O117: =J117*K117 -> 26234.25 | P117: =Table1[[#This Row],[Annual Salary]]+Table1[[#This Row],[Bonus Amount]] -> 201129.25 | Q117: =IF(Table1[[#This Row],[Exit Date]]="", "Active","Exited") -> Active | R117: =IFERROR(DATEDIF(Table1[[#This Row],[Hire Date]],IF(Table1[[#This Row],[Exit Date]]="",TODAY(),Table1[[#This Row],[Exit Date]]),"Y"),"") -> 27 | S117: {=_xlfn.IFS(Table1[[#This Row],[Age]]<30,"Under 30",Table1[[#This Row],[Age]]<=40,"30-40",Table1[[#This Row],[Age]]<50,"41-50",TRUE,"50+")} -> 50+
A118: E01642 | B118: Mia Lam | C118: Sr. Manger | D118: IT | E118: Manufacturing | F118: Female | G118: Asian | H118: 49 | I118: 38825 | J118: 134486 | K118: 0.14 | L118: United States | M118: Austin | O118: =J118*K118 -> 18828.04 | P118: =Table1[[#This Row],[Annual Salary]]+Table1[[#This Row],[Bonus Amount]] -> 153314.04 | Q118: =IF(Table1[[#This Row],[Exit Date]]="", "Active","Exited") -> Active | R118: =IFERROR(DATEDIF(Table1[[#This Row],[Hire Date]],IF(Table1[[#This Row],[Exit Date]]="",TODAY(),Table1[[#This Row],[Exit Date]]),"Y"),"") -> 19 | S118: {=_xlfn.IFS(Table1[[#This Row],[Age]]<30,"Under 30",Table1[[#This Row],[Age]]<=40,"30-40",Table1[[#This Row],[Age]]<50,"41-50",TRUE,"50+")} -> 41-50
... A131: E01095 | B131: Isla Lai | C131: Vice President | D131: Finance | E131: Corporate | F131: Female | G131: Asian | H131: 37 | I131: 40883 | J131: 225558 | K131: 0.33 | L131: China | M131: Shanghai | O131: =J131*K131 -> 74434.14 | P131: =Table1[[#This Row],[Annual Salary]]+Table1[[#This Row],[Bonus Amount]] -> 299992.14 | Q131: =IF(Table1[[#This Row],[Exit Date]]="", "Active","Exited") -> Active | R131: =IFERROR(DATEDIF(Table1[[#This Row],[Hire Date]],IF(Table1[[#This Row],[Exit Date]]="",TODAY(),Table1[[#This Row],[Exit Date]]),"Y"),"") -> 14 | S131: {=_xlfn.IFS(Table1[[#This Row],[Age]]<30,"Under 30",Table1[[#This Row],[Age]]<=40,"30-40",Table1[[#This Row],[Age]]<50,"41-50",TRUE,"50+")} -> 30-40
...

Sheet KPI_Helper
A1: Total Employees | B1: Total Salary Cost | C1: Total Bonus Cost | D1: Total Compensation of Employees | E1: Avg Age | F1: Avg Tenure
A2: 1000 | B2: 113217365 | C2: 15873801 | D2: 1.2909117e+08 | E2: 44.382 | F2: 12.524 | K2: Row Labels | L2: Employee Count
K3: Active | L3: 915
K4: Exited | L4: 85
K5: Grand Total | L5: 1000
A13: Row Labels | B13: Average of Tenure
A14: Accounting | B14: 11.3125
A15: Engineering | B15: 12.886076
A16: Finance | B16: 12.65
A17: Human Resources | B17: 12.56
A18: IT | B18: 13.008299
A19: Marketing | B19: 11.541667
A20: Sales | B20: 12.814286
A21: Grand Total | B21: 12.524

Sheet DASHBOARD
B2: HR Analytics Dashboard
B4: =GETPIVOTDATA("Total Employees",KPI_Helper!A1) -> 1000 | E4: =GETPIVOTDATA("EEID",KPI_Helper!K2,"Employee Status","Active") -> 915 | H4: =GETPIVOTDATA("EEID",KPI_Helper!$K$2,"Employee Status","Exited") -> 85 | K4: =GETPIVOTDATA("Avg Tenure",KPI_Helper!F1) -> 12.524 | N4: =H4/B4 -> 0.085
B5: Total Employees | E5: Active Employees | H5: Exited Employees | K5: Avg Tenure | N5: Attrition Rate %
B7: =GETPIVOTDATA("Total Salary Cost",KPI_Helper!B1) -> 113217365 | E7: =GETPIVOTDATA("Total Bonus Cost",KPI_Helper!C2) -> 15873801 | H7: =GETPIVOTDATA("Total Compensation of Employees",KPI_Helper!D2) -> 1.2909117e+08 | K7: =GETPIVOTDATA("Avg Age",KPI_Helper!E1) -> 44.382 | N7: =E4/B4 -> 0.915
B8: Total Salary Cost | E8: Total Bonus Cost | H8: Total Compensation | K8: Avg Age | N8: Retention Rate

Sheet Salary_Helper
A1: Row Labels | B1: Average of Annual Salary
A2: Vice President | B2: 222195.17
A3: Director | B3: 171633.85
A4: Sr. Manger | B4: 141067.76
A5: Manager | B5: 113275.68
A6: Engineering Manager | B6: 101853.8
A7: Operations Engineer | B7: 101135.25
A8: Controls Engineer | B8: 99626.133
A9: Automation Engineer | B9: 95106.857
A10: Cloud Infrastructure Architect | B10: 86961.333
A11: Sr. Analyst | B11: 86402.957
A12: Sr. Business Partner | B12: 85035.353
A13: Sr. Account Representative | B13: 84808.222
... A35: Grand Total | B35: 113217.37

Sheet Dept_Headcount_Helper
A1: Row Labels | B1: Count of EEID
A2: Accounting | B2: 96
A3: Finance | B3: 120
A4: Marketing | B4: 120
A5: Human Resources | B5: 125
A6: Sales | B6: 140
A7: Engineering | B7: 158
A8: IT | B8: 241
A9: Grand Total | B9: 1000

Sheet Gender_Helper
A1: Row Labels | B1: Count of EEID
A2: Female | B2: 518
A3: Male | B3: 482
A4: Grand Total | B4: 1000

Sheet Attrition_Helper
A1: Count of EEID | B1: Column Labels
A2: Row Labels | B2: Active | C2: Exited | D2: Grand Total
A3: Accounting | B3: 89 | C3: 7 | D3: 96
A4: Engineering | B4: 141 | C4: 17 | D4: 158
A5: Finance | B5: 111 | C5: 9 | D5: 120
A6: Human Resources | B6: 114 | C6: 11 | D6: 125
A7: IT | B7: 225 | C7: 16 | D7: 241
A8: Marketing | B8: 105 | C8: 15 | D8: 120
A9: Sales | B9: 130 | C9: 10 | D9: 140
A10: Grand Total | B10: 915 | C10: 85 | D10: 1000

Sheet Country_Helper
A2: Row Labels | B2: Count of EEID
A3: United States | B3: 643
A4: China | B4: 218
A5: Brazil | B5: 139
A6: Grand Total | B6: 1000
